{
	"title": "內容農場「密訊」重現 2018 盛況，Facebook 粉專分享總數高居第 2，助長旺中內容傳播",
	"subtitle": "IORG 心慌週報第 33 期 2022.7.1-10.31",
	"coverImage": "https://lh4.googleusercontent.com/dIIacEoTCtudeXpF7y1uivaC6TbUaFQSeI7aDhxsTNl-yMdnrbO9HxnilRgf0bdViKx3VQQ3QYYoq_VWsOAhlBrQ95SOOmC-Pczx9T0R1FNl5Ch52bxCdD2onufzIs_8DAPKvQJPVKNJ9nB3IeA4HgzcZCKgzcTO6Hig03ARjvDJ9FZRJo0K6yY",
	"authorInfoItemsHTML": "<li class=\"c0 c23 li-bullet-0\"><span class=\"c8\">作者 = IORG</span></li>",
	"tags": [
		"心慌週報"
	],
	"html": "<div class=\"stickers\"></div><h2 class=\"c16\" id=\"section-0\"><span class=\"c19\">摘要</span></h2><ul class=\"\"><li class=\"c14 li-bullet-0\"><span class=\"c8\">關於選舉，Facebook 華語粉專分享連結以新聞網站為主，「TVBS 新聞網」是分享總數最多的域名，「旺中集團」則為分享總數最高的媒體集團。</span></li><li class=\"c14 li-bullet-0\"><span>內容農場「密訊」於 2019 年曾被 Facebook「下架」，《</span><span class=\"c5\"><a class=\"c13\" href=\"https://www.twreporter.org/a/information-warfare-business-content-farm-mission\">報導者</a></span><span class=\"c8\">》亦曾揭露其中國因素。2019 年底開始，「密訊」以新的域名 pplomo 持續在 Facebook 傳播，此次選舉期間，成為分享總數第 2 名的域名，超過 YouTube 及大多數台灣新聞媒體。</span></li><li class=\"c14 li-bullet-0\"><span class=\"c8\">「藍色力量」、「青天白日正義力量」是分享「密訊」次數最多的粉專，也是最常進入提及各縣市長候選人貼文數量前 10 名的粉專。<a href=\"/da/31\" target=\"_blank\" class=\"da\"><span>DA.31</span></a></span></li><li class=\"c14 li-bullet-0\"><span class=\"c8\">綜合 IORG 研究、學者研究、新聞報導，內容農場「密訊」不只重生，而是已重現 2018 年選舉期間的傳播盛況。</span></li><li class=\"c14 li-bullet-0\"><span class=\"c8\">根據標題、內文及圖片內容分析，內容農場「密訊」內容至少過半來自「中時新聞網」。</span></li><li class=\"c14 li-bullet-0\"><span>旺中集團是分享總數最高的媒體集團，而「密訊」的內容主要來自中時，且為分享總數第 2 的域名。此次選舉期間，旺中集團對 Facebook 華語內容的重要性不容小覷。</span></li></ul><div class=\"stickers\"></div><h2 class=\"c16\" id=\"section-1\"><span class=\"c19\">資料來源</span></h2><ul class=\"\"><li class=\"c14 li-bullet-0\"><span class=\"c8\">2022 年 7 月 1 日至 10 月 31 日期間，IORG 資料庫備份約 4,332 萬則 Facebook 華語粉專貼文，其中 16.2 萬則內容提及 2022 年台灣地方選舉共 95 名縣市長候選人的姓名，納入本次報告範疇。</span></li></ul><div class=\"gdoc-table-container\"><div class=\"table\"><table class=\"c15\"><tbody><tr class=\"c2\"><th class=\"\" colspan=\"1\" rowspan=\"1\"><p>報告用語</p></th><th class=\"\" colspan=\"1\" rowspan=\"1\"><p>符合以下搜尋條件之聯集</p></th></tr><tr class=\"c2\"><td class=\"\" colspan=\"1\" rowspan=\"1\"><p>提及選舉；關於選舉</p></td><td class=\"\" colspan=\"1\" rowspan=\"1\"><ul class=\"\"><li class=\"c0 c23 li-bullet-0\"><span class=\"c1\">全國各縣市長候選人全名</span></li><li class=\"c0 c23 li-bullet-0\"><span class=\"c1\">Kolas</span></li><li class=\"c0 c23 li-bullet-0\"><span class=\"c1\">谷辣斯</span></li><li class=\"c0 c23 li-bullet-0\"><span class=\"c1\">林智堅</span></li></ul></td></tr></tbody></table></div><p class=\"c16 description\" id=\"h.z89i1t65b059\"><span class=\"c22\">報告用語及搜尋條件對照表。南投縣長候選人王永慶與已故企業家同名，為避免資料分析偏差，排除於搜尋條件之外；花蓮縣長候選人 Kolas Yotaka 谷辣斯･尤達卡全名較長，且可能包含標點符號，為避免資料分析偏差，搜尋條件改採「Kolas」及「谷辣斯」；林智堅曾為桃園市長候選人，納入搜尋條件。合計納入本期報告搜尋條件的政治人物，共 95 位。IORG 製表。</span></p></div><div class=\"gdoc-table-container\"><div class=\"table\"><table class=\"c15\"><tbody><tr class=\"c2\"><th class=\"\" colspan=\"1\" rowspan=\"1\"><p>資料集</p></th><th class=\"\" colspan=\"1\" rowspan=\"1\"><p>文本總量</p></th><th class=\"\" colspan=\"1\" rowspan=\"1\"><p>提及選舉文本數量</p></th></tr><tr class=\"c2\"><td class=\"\" colspan=\"1\" rowspan=\"1\"><p>Facebook 粉專</p></td><td class=\"number\" colspan=\"1\" rowspan=\"1\"><p>43,315,494</p></td><td class=\"number\" colspan=\"1\" rowspan=\"1\"><p>162,300</p></td></tr></tbody></table></div><p class=\"c16 description\" id=\"h.4czwqgusb7p\"><span class=\"c22\">2022 年 7 月 1 日至 2022 年 10 月 31 日間 IORG 資料庫 Faceook 粉專貼文文本總數及提及選舉的文本數量。資料來源：IORG 資料庫；IORG 製表。</span></p></div><div class=\"stickers\"></div><h2 class=\"c16\" id=\"section-2\"><span class=\"c19\">粉專分享連結：TVBS 單一網域最多、旺中集團合計最多</span></h2><ul class=\"\"><li class=\"c14 li-bullet-0\"><span class=\"c8\">提及 95 位候選人的 Facebook 華語粉專貼文共計 162,300 則，其中 80,362 則有分享連結，連結的域名（domain name）多為新聞網站。</span></li><li class=\"c14 li-bullet-0\"><span>以單一域名來看，TVBS 新聞網 </span><span>news.tvbs.com.tw 獲分享 </span><span class=\"c8\">4,955 次為最多。</span></li><li class=\"c14 li-bullet-0\"><span>以媒體集團來看，旺中集團旗下多個網站獲分享共計 6,005 次為最多，包括中天新聞網 </span><span>gotv.ctitv.com.tw</span><span> / </span><span>ctinews.com 及</span><span>中時新聞網 </span><span>www.chinatimes.com。</span></li><li class=\"c14 li-bullet-0\"><span>內容農場「密訊」</span><span>www.pplomo.com 獲分享 4,281 次，</span><span class=\"c8\">排名第 2，不只超過多數台灣新聞媒體，也超過世界最大的影片分享平台 YouTube。</span></li></ul><div class=\"gdoc-table-container\"><div class=\"table\"><table class=\"c15\"><tbody><tr class=\"c2\"><th class=\"w-4\" colspan=\"1\" rowspan=\"1\"><p>排名 </p></th><th class=\"w-12\" colspan=\"1\" rowspan=\"1\"><p>域名 </p></th><th class=\"w-12\" colspan=\"1\" rowspan=\"1\"><p>名稱 </p></th><th class=\"w-4\" colspan=\"1\" rowspan=\"1\"><p>分享數 </p></th></tr><tr class=\"c2\"><td class=\"w-4 number\" colspan=\"1\" rowspan=\"1\"><p>1</p></td><td class=\"w-12\" colspan=\"1\" rowspan=\"1\"><p class=\"c0\"><span class=\"c5 c3\"><a class=\"c13\" href=\"http://news.tvbs.com.tw\">news.tvbs.com.tw</a></span></p></td><td class=\"w-12\" colspan=\"1\" rowspan=\"1\"><p>TVBS 新聞網</p></td><td class=\"w-4 number\" colspan=\"1\" rowspan=\"1\"><p>4,955</p></td></tr><tr class=\"c2\"><td class=\"w-4 number\" colspan=\"1\" rowspan=\"1\"><p>2</p></td><td class=\"w-12\" colspan=\"1\" rowspan=\"1\"><p class=\"c0\"><span class=\"c5 c3\"><a class=\"c13\" href=\"http://www.pplomo.com\">www.pplomo.com</a></span></p></td><td class=\"w-12\" colspan=\"1\" rowspan=\"1\"><p>密訊</p></td><td class=\"w-4 number\" colspan=\"1\" rowspan=\"1\"><p>4,281</p></td></tr><tr class=\"c2\"><td class=\"w-4 number\" colspan=\"1\" rowspan=\"1\"><p>3</p></td><td class=\"w-12\" colspan=\"1\" rowspan=\"1\"><p class=\"c0\"><span class=\"c5 c3\"><a class=\"c13\" href=\"http://www.youtube.com\">www.youtube.com</a></span></p></td><td class=\"w-12\" colspan=\"1\" rowspan=\"1\"><p>YouTube</p></td><td class=\"w-4 number\" colspan=\"1\" rowspan=\"1\"><p>4,109</p></td></tr><tr class=\"c2\"><td class=\"w-4 number\" colspan=\"1\" rowspan=\"1\"><p>4</p></td><td class=\"w-12\" colspan=\"1\" rowspan=\"1\"><p class=\"c0\"><span class=\"c5 c3\"><a class=\"c13\" href=\"http://news.ltn.com.tw\">news.ltn.com.tw</a></span></p></td><td class=\"w-12\" colspan=\"1\" rowspan=\"1\"><p>自由時報</p></td><td class=\"w-4 number\" colspan=\"1\" rowspan=\"1\"><p>3,074</p></td></tr><tr class=\"c2\"><td class=\"w-4 number\" colspan=\"1\" rowspan=\"1\"><p>5</p></td><td class=\"w-12\" colspan=\"1\" rowspan=\"1\"><p class=\"c0\"><span class=\"c5 c3\"><a class=\"c13\" href=\"http://gotv.ctitv.com.tw\">gotv.ctitv.com.tw</a></span></p></td><td class=\"w-12\" colspan=\"1\" rowspan=\"1\"><p>中天新聞網</p></td><td class=\"w-4 number\" colspan=\"1\" rowspan=\"1\"><p>3,041</p></td></tr><tr class=\"c2\"><td class=\"w-4 number\" colspan=\"1\" rowspan=\"1\"><p>6</p></td><td class=\"w-12\" colspan=\"1\" rowspan=\"1\"><p class=\"c0\"><span class=\"c5 c3\"><a class=\"c13\" href=\"http://udn.com\">udn.com</a></span></p></td><td class=\"w-12\" colspan=\"1\" rowspan=\"1\"><p>聯合新聞網</p></td><td class=\"w-4 number\" colspan=\"1\" rowspan=\"1\"><p>2,620</p></td></tr><tr class=\"c2\"><td class=\"w-4 number\" colspan=\"1\" rowspan=\"1\"><p>7</p></td><td class=\"w-12\" colspan=\"1\" rowspan=\"1\"><p class=\"c0\"><span class=\"c5 c3\"><a class=\"c13\" href=\"http://newtalk.tw\">newtalk.tw</a></span></p></td><td class=\"w-12\" colspan=\"1\" rowspan=\"1\"><p>Newtalk 新聞</p></td><td class=\"w-4 number\" colspan=\"1\" rowspan=\"1\"><p>2,521</p></td></tr><tr class=\"c2\"><td class=\"w-4 number\" colspan=\"1\" rowspan=\"1\"><p>8</p></td><td class=\"w-12\" colspan=\"1\" rowspan=\"1\"><p class=\"c0\"><span class=\"c5 c3\"><a class=\"c13\" href=\"http://www.ettoday.net\">www.ettoday.net</a></span></p></td><td class=\"w-12\" colspan=\"1\" rowspan=\"1\"><p>ETtoday</p></td><td class=\"w-4 number\" colspan=\"1\" rowspan=\"1\"><p>2,472</p></td></tr><tr class=\"c2\"><td class=\"w-4 number\" colspan=\"1\" rowspan=\"1\"><p>9</p></td><td class=\"w-12\" colspan=\"1\" rowspan=\"1\"><p class=\"c0\"><span class=\"c5 c3\"><a class=\"c13\" href=\"http://tw.news.yahoo.com\">tw.news.yahoo.com</a></span></p></td><td class=\"w-12\" colspan=\"1\" rowspan=\"1\"><p>Yahoo 奇摩新聞</p></td><td class=\"w-4 number\" colspan=\"1\" rowspan=\"1\"><p>1,683</p></td></tr><tr class=\"c2\"><td class=\"w-4 number\" colspan=\"1\" rowspan=\"1\"><p>10</p></td><td class=\"w-12\" colspan=\"1\" rowspan=\"1\"><p class=\"c0\"><span class=\"c5 c3\"><a class=\"c13\" href=\"http://ctinews.com\">ctinews.com</a></span></p></td><td class=\"w-12\" colspan=\"1\" rowspan=\"1\"><p>中天新聞網</p></td><td class=\"w-4 number\" colspan=\"1\" rowspan=\"1\"><p>1,592</p></td></tr><tr class=\"c2\"><td class=\"w-4 number\" colspan=\"1\" rowspan=\"1\"><p>11</p></td><td class=\"w-12\" colspan=\"1\" rowspan=\"1\"><p class=\"c0\"><span class=\"c5 c3\"><a class=\"c13\" href=\"http://www.chinatimes.com\">www.chinatimes.com</a></span></p></td><td class=\"w-12\" colspan=\"1\" rowspan=\"1\"><p>中視新聞網</p></td><td class=\"w-4 number\" colspan=\"1\" rowspan=\"1\"><p>1,372</p></td></tr><tr class=\"c2\"><td class=\"w-4 number\" colspan=\"1\" rowspan=\"1\"><p>12</p></td><td class=\"w-12\" colspan=\"1\" rowspan=\"1\"><p class=\"c0\"><span class=\"c5 c3\"><a class=\"c13\" href=\"http://www.nownews.com\">www.nownews.com</a></span></p></td><td class=\"w-12\" colspan=\"1\" rowspan=\"1\"><p>NOWnews 今日新聞</p></td><td class=\"w-4 number\" colspan=\"1\" rowspan=\"1\"><p>936</p></td></tr><tr class=\"c2\"><td class=\"w-4 number\" colspan=\"1\" rowspan=\"1\"><p>13</p></td><td class=\"w-12\" colspan=\"1\" rowspan=\"1\"><p class=\"c0\"><span class=\"c5 c3\"><a class=\"c13\" href=\"http://www.setn.com\">www.setn.com</a></span></p></td><td class=\"w-12\" colspan=\"1\" rowspan=\"1\"><p>三立新聞</p></td><td class=\"w-4 number\" colspan=\"1\" rowspan=\"1\"><p>933</p></td></tr><tr class=\"c2\"><td class=\"w-4 number\" colspan=\"1\" rowspan=\"1\"><p>14</p></td><td class=\"w-12\" colspan=\"1\" rowspan=\"1\"><p class=\"c0\"><span class=\"c3 c5\"><a class=\"c13\" href=\"http://tyenews.com\">tyenews.com</a></span></p></td><td class=\"w-12\" colspan=\"1\" rowspan=\"1\"><p>桃園電子報</p></td><td class=\"w-4 number\" colspan=\"1\" rowspan=\"1\"><p>878</p></td></tr><tr class=\"c2\"><td class=\"w-4 number\" colspan=\"1\" rowspan=\"1\"><p>15</p></td><td class=\"w-12\" colspan=\"1\" rowspan=\"1\"><p class=\"c0\"><span class=\"c5 c3\"><a class=\"c13\" href=\"http://www.bfptt.cc\">www.bfptt.cc</a></span></p></td><td class=\"w-12\" colspan=\"1\" rowspan=\"1\"><p>BFPTT</p></td><td class=\"w-4 number\" colspan=\"1\" rowspan=\"1\"><p>570</p></td></tr><tr class=\"c2\"><td class=\"w-4 number\" colspan=\"1\" rowspan=\"1\"><p>16</p></td><td class=\"w-12\" colspan=\"1\" rowspan=\"1\"><p class=\"c0\"><span class=\"c5 c3\"><a class=\"c13\" href=\"http://news.ttv.com.tw\">news.ttv.com.tw</a></span></p></td><td class=\"w-12\" colspan=\"1\" rowspan=\"1\"><p>台視新聞網</p></td><td class=\"w-4 number\" colspan=\"1\" rowspan=\"1\"><p>546</p></td></tr><tr class=\"c2\"><td class=\"w-4 number\" colspan=\"1\" rowspan=\"1\"><p>17</p></td><td class=\"w-12\" colspan=\"1\" rowspan=\"1\"><p class=\"c0\"><span class=\"c5 c3\"><a class=\"c13\" href=\"http://news.pts.org.tw\">news.pts.org.tw</a></span></p></td><td class=\"w-12\" colspan=\"1\" rowspan=\"1\"><p>公視新聞網</p></td><td class=\"w-4 number\" colspan=\"1\" rowspan=\"1\"><p>498</p></td></tr><tr class=\"c2\"><td class=\"w-4 number\" colspan=\"1\" rowspan=\"1\"><p>18</p></td><td class=\"w-12\" colspan=\"1\" rowspan=\"1\"><p class=\"c0\"><span class=\"c5 c3\"><a class=\"c13\" href=\"http://cnews.com.tw\">cnews.com.tw</a></span></p></td><td class=\"w-12\" colspan=\"1\" rowspan=\"1\"><p>匯流新聞網</p></td><td class=\"w-4 number\" colspan=\"1\" rowspan=\"1\"><p>473</p></td></tr><tr class=\"c2\"><td class=\"w-4 number\" colspan=\"1\" rowspan=\"1\"><p>19</p></td><td class=\"w-12\" colspan=\"1\" rowspan=\"1\"><p class=\"c0\"><span class=\"c5 c3\"><a class=\"c13\" href=\"http://www.fountmedia.io\">www.fountmedia.io</a></span></p></td><td class=\"w-12\" colspan=\"1\" rowspan=\"1\"><p>放言 Fount Media</p></td><td class=\"w-4 number\" colspan=\"1\" rowspan=\"1\"><p>440</p></td></tr><tr class=\"c2\"><td class=\"w-4 number\" colspan=\"1\" rowspan=\"1\"><p>20</p></td><td class=\"w-12\" colspan=\"1\" rowspan=\"1\"><p class=\"c0\"><span class=\"c5 c3\"><a class=\"c13\" href=\"http://taronews.tw\">taronews.tw</a></span></p></td><td class=\"w-12\" colspan=\"1\" rowspan=\"1\"><p>芋傳媒</p></td><td class=\"w-4 number\" colspan=\"1\" rowspan=\"1\"><p>418</p></td></tr></tbody></table></div></div><div class=\"stickers\"></div><h2 class=\"c16\" id=\"section-3\"><span>內容農場「密訊」重現 2018 </span><span>選舉期間盛況</span></h2><ul class=\"\"><li class=\"c14 li-bullet-0\"><span>內容農場「密訊」於 2019 年曾被 Facebook「下架」，《</span><span class=\"c5\"><a class=\"c13\" href=\"https://www.twreporter.org/a/information-warfare-business-content-farm-mission\">報導者</a></span><span class=\"c8\">》亦曾揭露其中國因素。2019 年 11 月 27 日期，「密訊」以新的域名 pplomo「重生」，並持續在 Facebook 傳播，未受 Facebook 限制。</span></li><li class=\"c14 li-bullet-0\"><span>根據上述 IORG 分析，此次選舉期間，「密訊」成為獲 Facebook 粉專分享總數第 2 名的域名，超過 YouTube 及大多數台灣新聞媒體。</span></li><li class=\"c14 li-bullet-0\"><span>根據《</span><span class=\"c5\"><a class=\"c13\" href=\"https://www.twreporter.org/a/information-warfare-business-content-farm-mission\">報導者</a></span><span class=\"c8\">》報導，「密訊」 在 2019 年 4 月為單週 Facebook 分享次數最多的域名，超越第 2 名「自由時報」 5 倍。</span></li><li class=\"c14 li-bullet-0\"><span>根據《</span><span class=\"c5\"><a class=\"c13\" href=\"https://www.twreporter.org/a/information-warfare-business-content-farm-mission\">報導者</a></span><span>》報導</span><span>政治大學新聞系副教授鄭宇君的研究，2018 年選舉前夕，「密訊」在支持國民黨的粉絲專頁之中分享</span><span class=\"c8\">次數排名第 2。</span></li><li class=\"c14 li-bullet-0\"><span class=\"c8\">自第 3 期週報起，IORG 共發布 6 期週報紀錄多個 Facebook 華語粉專群聚分享「密訊」文章，內容涉及各個議題。</span></li><li class=\"c14 li-bullet-0\"><span class=\"c8\">去年 2021 年 4-8 月期間，關於高端、BNT 的 Facebook 貼文分享，「密訊」獲分享次數超過多個台灣新聞媒體，包括風傳媒、TVBS、中國時報、自由時報。<a href=\"/da/13\" target=\"_blank\" class=\"da\"><span>DA.13</span></a></span></li><li class=\"c14 li-bullet-0\"><span>「</span><span class=\"c5\"><a class=\"c13\" href=\"https://www.facebook.com/851884711574981\">藍色力量</a></span><span>」、「</span><span class=\"c5\"><a class=\"c13\" href=\"https://www.facebook.com/1006889099430655\">青天白日正義力量</a></span><span class=\"c8\">」是分享「密訊」次數最多的粉專，也是最常進入提及各縣市長候選人貼文數量前 10 名的粉專。<a href=\"/da/31\" target=\"_blank\" class=\"da\"><span>DA.31</span></a></span></li><li class=\"c14 li-bullet-0\"><span class=\"c8\">綜合 IORG 研究、學者研究、新聞報導，曾經被 Facebook「下架」的「密訊」不只重生，可能已重現 2018 年選舉期間的盛況。</span></li></ul><div class=\"gdoc-table-container\"><div class=\"table\"><table class=\"c15\"><tbody><tr class=\"c2\"><th class=\"w-4\" colspan=\"1\" rowspan=\"1\"><p>排名 </p></th><th class=\"w-16\" colspan=\"1\" rowspan=\"1\"><p>粉專 </p></th><th class=\"w-4\" colspan=\"1\" rowspan=\"1\"><p>密訊分享數 </p></th></tr><tr class=\"c2\"><td class=\"w-4 number\" colspan=\"1\" rowspan=\"1\"><p>1</p></td><td class=\"w-16\" colspan=\"1\" rowspan=\"1\"><p class=\"c0\"><span class=\"c5 c3\"><a class=\"c13\" href=\"https://www.facebook.com/851884711574981\">藍色力量</a></span></p></td><td class=\"w-4 number\" colspan=\"1\" rowspan=\"1\"><p>1,947</p></td></tr><tr class=\"c2\"><td class=\"w-4 number\" colspan=\"1\" rowspan=\"1\"><p>2</p></td><td class=\"w-16\" colspan=\"1\" rowspan=\"1\"><p class=\"c0\"><span class=\"c5 c3\"><a class=\"c13\" href=\"https://www.facebook.com/1006889099430655\">青天白日正義力量</a></span></p></td><td class=\"w-4 number\" colspan=\"1\" rowspan=\"1\"><p>1,282</p></td></tr><tr class=\"c2\"><td class=\"w-4 number\" colspan=\"1\" rowspan=\"1\"><p>3</p></td><td class=\"w-16\" colspan=\"1\" rowspan=\"1\"><p class=\"c0\"><span class=\"c5 c3\"><a class=\"c13\" href=\"https://www.facebook.com/1005354439549606\">民間大小事</a></span></p></td><td class=\"w-4 number\" colspan=\"1\" rowspan=\"1\"><p>407</p></td></tr><tr class=\"c2\"><td class=\"w-4 number\" colspan=\"1\" rowspan=\"1\"><p>4</p></td><td class=\"w-16\" colspan=\"1\" rowspan=\"1\"><p class=\"c0\"><span class=\"c5 c3\"><a class=\"c13\" href=\"https://www.facebook.com/1067024713417898\">反民進黨粉絲團</a></span></p></td><td class=\"w-4 number\" colspan=\"1\" rowspan=\"1\"><p>298</p></td></tr><tr class=\"c2\"><td class=\"w-4 number\" colspan=\"1\" rowspan=\"1\"><p>5</p></td><td class=\"w-16\" colspan=\"1\" rowspan=\"1\"><p class=\"c0\"><span class=\"c5 c3\"><a class=\"c13\" href=\"https://www.facebook.com/1113496565391244\">空心菜政府</a></span></p></td><td class=\"w-4 number\" colspan=\"1\" rowspan=\"1\"><p>274</p></td></tr><tr class=\"c2\"><td class=\"w-4 number\" colspan=\"1\" rowspan=\"1\"><p>6</p></td><td class=\"w-16\" colspan=\"1\" rowspan=\"1\"><p class=\"c0\"><span class=\"c5 c3\"><a class=\"c13\" href=\"https://www.facebook.com/1100522356652838\">藍色正義力量</a></span></p></td><td class=\"w-4 number\" colspan=\"1\" rowspan=\"1\"><p>70</p></td></tr><tr class=\"c2\"><td class=\"w-4 number\" colspan=\"1\" rowspan=\"1\"><p>7</p></td><td class=\"w-16\" colspan=\"1\" rowspan=\"1\"><p class=\"c0\"><span class=\"c5 c3\"><a class=\"c13\" href=\"https://www.facebook.com/100064786866464\">中國國民黨竹東鎮黨部</a></span></p></td><td class=\"w-4 number\" colspan=\"1\" rowspan=\"1\"><p>2</p></td></tr><tr class=\"c2\"><td class=\"w-4 number\" colspan=\"1\" rowspan=\"1\"><p>8</p></td><td class=\"w-16\" colspan=\"1\" rowspan=\"1\"><p class=\"c0\"><span class=\"c5 c3\"><a class=\"c13\" href=\"https://www.facebook.com/100044400285139\">村長 詹江村全球後援會粉絲團</a></span></p></td><td class=\"w-4 number\" colspan=\"1\" rowspan=\"1\"><p>1</p></td></tr></tbody></table></div></div><div class=\"stickers\"></div><h2 class=\"c16\" id=\"section-4\"><span class=\"c19\">「密訊」內容至少過半來自「中時新聞網」</span></h2><ul class=\"\"><li class=\"c14 li-bullet-0\"><span class=\"c8\">根據 IORG 資料庫，2022 年 7 月 1 日至 10 月 31 日期間，「密訊」共發布 10,907 則文章。</span></li><li class=\"c14 li-bullet-0\"><span class=\"c8\">比對「密訊」文章和同期台灣新聞報導內容，發現 5,003 則（45.87%）「密訊」文章和「中時新聞網」報導標題完全相同。</span></li><li class=\"c14 li-bullet-0\"><span class=\"c8\">觀察「密訊」文章嵌入的圖片網址域名，發現 6,017 則（55.17%）「密訊」文章嵌入圖片來自「中時新聞網」。</span></li><li class=\"c14 li-bullet-0\"><span class=\"c8\">比對「密訊」和台灣新聞報導內容，發現 6,789 則（62.24%）「密訊」文章，其內文有超過 50% 的句子和「中時新聞網」報導內容完全相同。</span></li><li class=\"c14 li-bullet-0\"><span class=\"c8\">旺中集團是分享總數最高的媒體集團，而「密訊」的內容至少過半來自中時，且為分享總數第 2 的域名。此次選舉期間，旺中集團對 Facebook 華語內容的重要性不容小覷。</span></li></ul><div class=\"gdoc-table-container\"><div class=\"table\"><table class=\"c15\"><tbody><tr class=\"c2\"><th class=\"w-4\" colspan=\"1\" rowspan=\"1\"><p>排名 </p></th><th class=\"w-16\" colspan=\"1\" rowspan=\"1\"><p>域名 </p></th><th class=\"w-8\" colspan=\"1\" rowspan=\"1\"><p>名稱 </p></th><th class=\"w-4\" colspan=\"1\" rowspan=\"1\"><p>文章數 </p></th><th class=\"w-4\" colspan=\"1\" rowspan=\"1\"><p>% </p></th></tr><tr class=\"c2\"><td class=\"w-4 number\" colspan=\"1\" rowspan=\"1\"><p>1</p></td><td class=\"w-16\" colspan=\"1\" rowspan=\"1\"><p>chinatimes.com</p></td><td class=\"w-8\" colspan=\"1\" rowspan=\"1\"><p>中時新聞網</p></td><td class=\"w-4 number\" colspan=\"1\" rowspan=\"1\"><p>5,003</p></td><td class=\"w-4 number\" colspan=\"1\" rowspan=\"1\"><p>45.87%</p></td></tr><tr class=\"c2\"><td class=\"w-4 number\" colspan=\"1\" rowspan=\"1\"><p>2</p></td><td class=\"w-16\" colspan=\"1\" rowspan=\"1\"><p>udn.com</p></td><td class=\"w-8\" colspan=\"1\" rowspan=\"1\"><p>聯合新聞網</p></td><td class=\"w-4 number\" colspan=\"1\" rowspan=\"1\"><p>259</p></td><td class=\"w-4 number\" colspan=\"1\" rowspan=\"1\"><p>2.37%</p></td></tr><tr class=\"c2\"><td class=\"w-4 number\" colspan=\"1\" rowspan=\"1\"><p>3</p></td><td class=\"w-16\" colspan=\"1\" rowspan=\"1\"><p>cna.com.tw</p></td><td class=\"w-8\" colspan=\"1\" rowspan=\"1\"><p>中央社</p></td><td class=\"w-4 number\" colspan=\"1\" rowspan=\"1\"><p>28</p></td><td class=\"w-4 number\" colspan=\"1\" rowspan=\"1\"><p>0.26%</p></td></tr><tr class=\"c2\"><td class=\"w-4 number\" colspan=\"1\" rowspan=\"1\"><p>4</p></td><td class=\"w-16\" colspan=\"1\" rowspan=\"1\"><p>ctee.com.tw</p></td><td class=\"w-8\" colspan=\"1\" rowspan=\"1\"><p>工商時報</p></td><td class=\"w-4 number\" colspan=\"1\" rowspan=\"1\"><p>3</p></td><td class=\"w-4 number\" colspan=\"1\" rowspan=\"1\"><p>0.03%</p></td></tr><tr class=\"c2\"><td class=\"w-4 number\" colspan=\"1\" rowspan=\"1\"><p>5</p></td><td class=\"w-16\" colspan=\"1\" rowspan=\"1\"><p>newtalk.tw</p></td><td class=\"w-8\" colspan=\"1\" rowspan=\"1\"><p>Newtalk 新聞</p></td><td class=\"w-4 number\" colspan=\"1\" rowspan=\"1\"><p>2</p></td><td class=\"w-4 number\" colspan=\"1\" rowspan=\"1\"><p>0.02%</p></td></tr><tr class=\"c2\"><td class=\"w-4 number\" colspan=\"1\" rowspan=\"1\"><p>6</p></td><td class=\"w-16\" colspan=\"1\" rowspan=\"1\"><p>news.ltn.com.tw</p></td><td class=\"w-8\" colspan=\"1\" rowspan=\"1\"><p>自由時報</p></td><td class=\"w-4 number\" colspan=\"1\" rowspan=\"1\"><p>1</p></td><td class=\"w-4 number\" colspan=\"1\" rowspan=\"1\"><p>0.01%</p></td></tr><tr class=\"c2\"><td class=\"w-4 number\" colspan=\"1\" rowspan=\"1\"><p>7</p></td><td class=\"w-16\" colspan=\"1\" rowspan=\"1\"><p>setn.com</p></td><td class=\"w-8\" colspan=\"1\" rowspan=\"1\"><p>三立新聞網</p></td><td class=\"w-4 number\" colspan=\"1\" rowspan=\"1\"><p>1</p></td><td class=\"w-4 number\" colspan=\"1\" rowspan=\"1\"><p>0.01%</p></td></tr><tr class=\"c2\"><td class=\"w-4 number\" colspan=\"1\" rowspan=\"1\"><p>8</p></td><td class=\"w-16\" colspan=\"1\" rowspan=\"1\"><p>storm.mg</p></td><td class=\"w-8\" colspan=\"1\" rowspan=\"1\"><p>風傳媒</p></td><td class=\"w-4 number\" colspan=\"1\" rowspan=\"1\"><p>1</p></td><td class=\"w-4 number\" colspan=\"1\" rowspan=\"1\"><p>0.01%</p></td></tr></tbody></table></div><p class=\"c16 description\" id=\"h.geadfbz3dxnl\"><span class=\"c22\">和「密訊」文章標題完全相同的文章數量排名。資料來源：IORG 資料庫；IORG 製表。</span></p></div><div class=\"gdoc-table-container\"><div class=\"table\"><table class=\"c15\"><tbody><tr class=\"c2\"><th class=\"w-4\" colspan=\"1\" rowspan=\"1\"><p>排名 </p></th><th class=\"w-16\" colspan=\"1\" rowspan=\"1\"><p>域名 </p></th><th class=\"w-8\" colspan=\"1\" rowspan=\"1\"><p>名稱 </p></th><th class=\"w-4\" colspan=\"1\" rowspan=\"1\"><p>數量 </p></th><th class=\"w-4\" colspan=\"1\" rowspan=\"1\"><p>% </p></th></tr><tr class=\"c2\"><td class=\"w-4 number\" colspan=\"1\" rowspan=\"1\"><p>1</p></td><td class=\"w-16\" colspan=\"1\" rowspan=\"1\"><p>images.chinatimes.com</p></td><td class=\"w-8\" colspan=\"1\" rowspan=\"1\"><p>中時新聞網</p></td><td class=\"w-4 number\" colspan=\"1\" rowspan=\"1\"><p>6,017</p></td><td class=\"w-4 number\" colspan=\"1\" rowspan=\"1\"><p>55.17%</p></td></tr><tr class=\"c2\"><td class=\"w-4 number\" colspan=\"1\" rowspan=\"1\"><p>2</p></td><td class=\"w-16\" colspan=\"1\" rowspan=\"1\"><p>pplomo.com</p></td><td class=\"w-8\" colspan=\"1\" rowspan=\"1\"><p>密訊</p></td><td class=\"w-4 number\" colspan=\"1\" rowspan=\"1\"><p>345</p></td><td class=\"w-4 number\" colspan=\"1\" rowspan=\"1\"><p>3.16%</p></td></tr><tr class=\"c2\"><td class=\"w-4 number\" colspan=\"1\" rowspan=\"1\"><p>3</p></td><td class=\"w-16\" colspan=\"1\" rowspan=\"1\"><p>cc.tvbs.com.tw</p></td><td class=\"w-8\" colspan=\"1\" rowspan=\"1\"><p>TVBS 官方網站</p></td><td class=\"w-4 number\" colspan=\"1\" rowspan=\"1\"><p>131</p></td><td class=\"w-4 number\" colspan=\"1\" rowspan=\"1\"><p>1.20%</p></td></tr><tr class=\"c2\"><td class=\"w-4 number\" colspan=\"1\" rowspan=\"1\"><p>4</p></td><td class=\"w-16\" colspan=\"1\" rowspan=\"1\"><p>hkjrt1212.files.wordpress.com</p></td><td class=\"w-8\" colspan=\"1\" rowspan=\"1\"><p>巴基斯坦美食</p></td><td class=\"w-4 number\" colspan=\"1\" rowspan=\"1\"><p>22</p></td><td class=\"w-4 number\" colspan=\"1\" rowspan=\"1\"><p>0.20%</p></td></tr><tr class=\"c2\"><td class=\"w-4 number\" colspan=\"1\" rowspan=\"1\"><p>5</p></td><td class=\"w-16\" colspan=\"1\" rowspan=\"1\"><p>attach.mobile01.com</p></td><td class=\"w-8\" colspan=\"1\" rowspan=\"1\"><p>Mobile01</p></td><td class=\"w-4 number\" colspan=\"1\" rowspan=\"1\"><p>12</p></td><td class=\"w-4 number\" colspan=\"1\" rowspan=\"1\"><p>0.11%</p></td></tr><tr class=\"c2\"><td class=\"w-4 number\" colspan=\"1\" rowspan=\"1\"><p>6</p></td><td class=\"w-16\" colspan=\"1\" rowspan=\"1\"><p>i.imgur.com</p></td><td class=\"w-8\" colspan=\"1\" rowspan=\"1\"><p>Imgur</p></td><td class=\"w-4 number\" colspan=\"1\" rowspan=\"1\"><p>8</p></td><td class=\"w-4 number\" colspan=\"1\" rowspan=\"1\"><p>0.07%</p></td></tr><tr class=\"c2\"><td class=\"w-4 number\" colspan=\"1\" rowspan=\"1\"><p>7</p></td><td class=\"w-16\" colspan=\"1\" rowspan=\"1\"><p>tengsuh.com</p></td><td class=\"w-8\" colspan=\"1\" rowspan=\"1\"><p>藤素藥局</p></td><td class=\"w-4 number\" colspan=\"1\" rowspan=\"1\"><p>5</p></td><td class=\"w-4 number\" colspan=\"1\" rowspan=\"1\"><p>0.05%</p></td></tr><tr class=\"c2\"><td class=\"w-4 number\" colspan=\"1\" rowspan=\"1\"><p>8</p></td><td class=\"w-16\" colspan=\"1\" rowspan=\"1\"><p>vapetaiwan-media.com</p></td><td class=\"w-8\" colspan=\"1\" rowspan=\"1\"><p>台灣威卜 煙草減害網路媒體</p></td><td class=\"w-4 number\" colspan=\"1\" rowspan=\"1\"><p>5</p></td><td class=\"w-4 number\" colspan=\"1\" rowspan=\"1\"><p>0.05%</p></td></tr><tr class=\"c2\"><td class=\"w-4 number\" colspan=\"1\" rowspan=\"1\"><p>9</p></td><td class=\"w-16\" colspan=\"1\" rowspan=\"1\"><p>mmbiz.qpic.cn</p></td><td class=\"w-8\" colspan=\"1\" rowspan=\"1\"><p>-</p></td><td class=\"w-4 number\" colspan=\"1\" rowspan=\"1\"><p>4</p></td><td class=\"w-4 number\" colspan=\"1\" rowspan=\"1\"><p>0.04%</p></td></tr><tr class=\"c2\"><td class=\"w-4 number\" colspan=\"1\" rowspan=\"1\"><p>10</p></td><td class=\"w-16\" colspan=\"1\" rowspan=\"1\"><p>pettidy.com</p></td><td class=\"w-8\" colspan=\"1\" rowspan=\"1\"><p>犀利士部落格</p></td><td class=\"w-4 number\" colspan=\"1\" rowspan=\"1\"><p>4</p></td><td class=\"w-4 number\" colspan=\"1\" rowspan=\"1\"><p>0.04%</p></td></tr><tr class=\"c2\"><td class=\"w-4 number\" colspan=\"1\" rowspan=\"1\"><p>11</p></td><td class=\"w-16\" colspan=\"1\" rowspan=\"1\"><p>i2.kknews.cc</p></td><td class=\"w-8\" colspan=\"1\" rowspan=\"1\"><p>每日頭條</p></td><td class=\"w-4 number\" colspan=\"1\" rowspan=\"1\"><p>3</p></td><td class=\"w-4 number\" colspan=\"1\" rowspan=\"1\"><p>0.03%</p></td></tr></tbody></table></div><p class=\"c16 description\" id=\"h.wnyst8hd6d3e\"><span class=\"c22\">「密訊」文章嵌入的圖片來源域名標題完全相同的文章數量排名。資料來源：IORG 資料庫；IORG 製表。</span></p></div><div class=\"gdoc-table-container\"><div class=\"table\"><table class=\"c15\"><tbody><tr class=\"c2\"><th class=\"w-4\" colspan=\"1\" rowspan=\"1\"><p>排名 </p></th><th class=\"w-16\" colspan=\"1\" rowspan=\"1\"><p>域名 </p></th><th class=\"w-8\" colspan=\"1\" rowspan=\"1\"><p>名稱 </p></th><th class=\"w-4\" colspan=\"1\" rowspan=\"1\"><p>文章數 </p></th><th class=\"w-4\" colspan=\"1\" rowspan=\"1\"><p>% </p></th></tr><tr class=\"c2\"><td class=\"w-4 number\" colspan=\"1\" rowspan=\"1\"><p>1</p></td><td class=\"w-16\" colspan=\"1\" rowspan=\"1\"><p>chinatimes.com</p></td><td class=\"w-8\" colspan=\"1\" rowspan=\"1\"><p>中時新聞網</p></td><td class=\"w-4 number\" colspan=\"1\" rowspan=\"1\"><p>6789</p></td><td class=\"w-4 number\" colspan=\"1\" rowspan=\"1\"><p>62.24%</p></td></tr><tr class=\"c2\"><td class=\"w-4 number\" colspan=\"1\" rowspan=\"1\"><p>2</p></td><td class=\"w-16\" colspan=\"1\" rowspan=\"1\"><p>news.tvbs.com.tw</p></td><td class=\"w-8\" colspan=\"1\" rowspan=\"1\"><p>TVBS 新聞網</p></td><td class=\"w-4 number\" colspan=\"1\" rowspan=\"1\"><p>521</p></td><td class=\"w-4 number\" colspan=\"1\" rowspan=\"1\"><p>4.78%</p></td></tr><tr class=\"c2\"><td class=\"w-4 number\" colspan=\"1\" rowspan=\"1\"><p>3</p></td><td class=\"w-16\" colspan=\"1\" rowspan=\"1\"><p>udn.com</p></td><td class=\"w-8\" colspan=\"1\" rowspan=\"1\"><p>聯合新聞網</p></td><td class=\"w-4 number\" colspan=\"1\" rowspan=\"1\"><p>436</p></td><td class=\"w-4 number\" colspan=\"1\" rowspan=\"1\"><p>4.00%</p></td></tr><tr class=\"c2\"><td class=\"w-4 number\" colspan=\"1\" rowspan=\"1\"><p>4</p></td><td class=\"w-16\" colspan=\"1\" rowspan=\"1\"><p>setn.com</p></td><td class=\"w-8\" colspan=\"1\" rowspan=\"1\"><p>三立新聞網</p></td><td class=\"w-4 number\" colspan=\"1\" rowspan=\"1\"><p>248</p></td><td class=\"w-4 number\" colspan=\"1\" rowspan=\"1\"><p>2.27%</p></td></tr><tr class=\"c2\"><td class=\"w-4 number\" colspan=\"1\" rowspan=\"1\"><p>5</p></td><td class=\"w-16\" colspan=\"1\" rowspan=\"1\"><p>ettoday.net</p></td><td class=\"w-8\" colspan=\"1\" rowspan=\"1\"><p>ETtoday</p></td><td class=\"w-4 number\" colspan=\"1\" rowspan=\"1\"><p>181</p></td><td class=\"w-4 number\" colspan=\"1\" rowspan=\"1\"><p>1.66%</p></td></tr><tr class=\"c2\"><td class=\"w-4 number\" colspan=\"1\" rowspan=\"1\"><p>6</p></td><td class=\"w-16\" colspan=\"1\" rowspan=\"1\"><p>ctwant.com</p></td><td class=\"w-8\" colspan=\"1\" rowspan=\"1\"><p>CTWant</p></td><td class=\"w-4 number\" colspan=\"1\" rowspan=\"1\"><p>160</p></td><td class=\"w-4 number\" colspan=\"1\" rowspan=\"1\"><p>1.47%</p></td></tr><tr class=\"c2\"><td class=\"w-4 number\" colspan=\"1\" rowspan=\"1\"><p>7</p></td><td class=\"w-16\" colspan=\"1\" rowspan=\"1\"><p>newtalk.tw</p></td><td class=\"w-8\" colspan=\"1\" rowspan=\"1\"><p>Newtalk 新聞</p></td><td class=\"w-4 number\" colspan=\"1\" rowspan=\"1\"><p>104</p></td><td class=\"w-4 number\" colspan=\"1\" rowspan=\"1\"><p>0.95%</p></td></tr><tr class=\"c2\"><td class=\"w-4 number\" colspan=\"1\" rowspan=\"1\"><p>8</p></td><td class=\"w-16\" colspan=\"1\" rowspan=\"1\"><p>news.ltn.com.tw</p></td><td class=\"w-8\" colspan=\"1\" rowspan=\"1\"><p>自由時報</p></td><td class=\"w-4 number\" colspan=\"1\" rowspan=\"1\"><p>85</p></td><td class=\"w-4 number\" colspan=\"1\" rowspan=\"1\"><p>0.78%</p></td></tr><tr class=\"c2\"><td class=\"w-4 number\" colspan=\"1\" rowspan=\"1\"><p>9</p></td><td class=\"w-16\" colspan=\"1\" rowspan=\"1\"><p>cna.com.tw</p></td><td class=\"w-8\" colspan=\"1\" rowspan=\"1\"><p>中央社</p></td><td class=\"w-4 number\" colspan=\"1\" rowspan=\"1\"><p>79</p></td><td class=\"w-4 number\" colspan=\"1\" rowspan=\"1\"><p>0.72%</p></td></tr><tr class=\"c2\"><td class=\"w-4 number\" colspan=\"1\" rowspan=\"1\"><p>10</p></td><td class=\"w-16\" colspan=\"1\" rowspan=\"1\"><p>ctee.com.tw</p></td><td class=\"w-8\" colspan=\"1\" rowspan=\"1\"><p>工商時報</p></td><td class=\"w-4 number\" colspan=\"1\" rowspan=\"1\"><p>66</p></td><td class=\"w-4 number\" colspan=\"1\" rowspan=\"1\"><p>0.61%</p></td></tr><tr class=\"c2\"><td class=\"w-4 number\" colspan=\"1\" rowspan=\"1\"><p>11</p></td><td class=\"w-16\" colspan=\"1\" rowspan=\"1\"><p>storm.mg</p></td><td class=\"w-8\" colspan=\"1\" rowspan=\"1\"><p>風傳媒</p></td><td class=\"w-4 number\" colspan=\"1\" rowspan=\"1\"><p>59</p></td><td class=\"w-4 number\" colspan=\"1\" rowspan=\"1\"><p>0.54%</p></td></tr></tbody></table></div><p class=\"c16 description\" id=\"h.waey57lef5fu\"><span class=\"c22\">「密訊」文章內容和台灣新聞報導內容句子完全相同比例高於 50% 的文章數量排名。資料來源：IORG 資料庫；IORG 製表。</span></p></div>",
	"articleID": "_DA_33",
	"publicURL": "https://docs.google.com/document/d/e/2PACX-1vQG_oUSX-RlWKVvmvFQsHWebKmCSzt7D8ew3g6rtgEOVO-7RXhoEaCCbWeodZ-OG8epWoJh0Mt4SRUs/pub",
	"locale": "_tw",
	"publishedAt": "2022/11/18 12:00"
}