{
	"title": "中共月報：2025 年 11 月",
	"subtitle": "IORG 週報第 126 期 2025.11.1-30",
	"coverImage": "https://lh7-rt.googleusercontent.com/docsz/AD_4nXf7SgSqJrBoQejqlTVpuv3sxt8b7xQ9SJzlZlfst2cw7PXhz-83tDJKnWXLU7rpY7CC-Lfuj0e4Ewl8JJCRQi3goqsUcpGp1Nin-djMuKVbZLVMzMUixCSjBq_2O7rZnOs?key=WeF81vsYFdmWvkIXauX8HQ",
	"authorInfoItemsHTML": "<li class=\"c5 c21 li-bullet-0\"><span class=\"c7\">作者 = 台灣資訊環境研究中心 IORG</span></li>",
	"tags": [
		"月報",
		"上月中共",
		"Last Month China Talks"
	],
	"sections": [
		{
			"id": "h2-1",
			"titleText": "資料來源"
		},
		{
			"id": "h2-2",
			"titleText": "台灣政治人物及名嘴 Top 5：賴清德、鄭麗文、沈伯洋、陳之漢（館長）、陳柏源（閩南狼）、溫子瑜（八炯）"
		},
		{
			"id": "h2-3",
			"titleText": "精選時事"
		},
		{
			"id": "h2-4",
			"titleText": "精選影劇"
		},
		{
			"id": "h2-5",
			"titleText": "精選科技"
		},
		{
			"id": "h2-6",
			"titleText": "精選人物"
		},
		{
			"id": "h2-7",
			"titleText": "精選美食"
		}
	],
	"html": "<div class=\"gdoc-photo-container\"><div class=\"images\"><img alt=\"\" src=\"https://lh7-rt.googleusercontent.com/docsz/AD_4nXfoqchWhRfTx-2sZrTT1gKr2-XgW6UgZ89-3utoHBU-7NZn8Sest-hyrQiNEMzKIuGreSRFdy1po0gU9T8NWbeUrhVqEnpXd6CTuz2BhzbOvSyyfXu-oz0JqbO9D3CDfA?key=WeF81vsYFdmWvkIXauX8HQ\" title=\"\"></div><p class=\"description\"><span class=\"c7\">2025 年 11 月中共宣傳文本分析。資料來源：IORG 資料庫，台灣資訊環境研究中心 IORG 製作。</span></p></div><div class=\"separator\"></div><div class=\"gdoc-photo-container\"><div class=\"images\"><img alt=\"\" src=\"https://lh7-rt.googleusercontent.com/docsz/AD_4nXf7SgSqJrBoQejqlTVpuv3sxt8b7xQ9SJzlZlfst2cw7PXhz-83tDJKnWXLU7rpY7CC-Lfuj0e4Ewl8JJCRQi3goqsUcpGp1Nin-djMuKVbZLVMzMUixCSjBq_2O7rZnOs?key=WeF81vsYFdmWvkIXauX8HQ\" title=\"\"></div></div><div class=\"separator\"></div><div class=\"stickers\"></div><h2 class=\"c4\" id=\"h2-1\"><span class=\"c26\">資料來源</span></h2><ul class=\"\"><li class=\"\"><span class=\"c7\">2025 年 11 月 1-30 日間 IORG 資料庫共備份 35,999 則提及台灣的中共文本，來源包括中國政府組織、中國解放軍組織、中國政治組織、中共官媒、中共官媒品牌、中共官媒內容、中共官方連結媒體、中共官方認可媒體、中共官方認可網紅、中國國營企業、中國政治人物、香港官媒、澳門官媒。</span></li></ul><div class=\"separator\"></div><div class=\"stickers\"></div><h2 class=\"c4\" id=\"h2-2\"><span>台灣政治人物及名嘴 Top 5</span><span class=\"c26\">：賴清德、鄭麗文、沈伯洋、陳之漢（館長）、陳柏源（閩南狼）、溫子瑜（八炯）</span></h2><ul class=\"\"><li class=\"\"><span>11 月份共有 2,578 則中共文本提及賴清德，主要聚焦在批評賴清德 10 月 31 日出席國軍 M1A2T 戰車入列儀式的發言是「以武谋独」（</span><span class=\"c10\"><a class=\"c9\" href=\"http://www.mod.gov.cn/gfbw/xwfyr/yzxwfb/16420374.html\">国防部</a></span><span>）、宣稱網紅陳之漢（館長）前往福建「赖氏家庙」是替賴清德「寻根」（</span><span class=\"c10 c14\"><a class=\"c9\" href=\"https://www.douyin.com/video/7571625043281628470\">中国台湾网</a></span><span>）、批評賴清德在高市早苗「若中共對台動武，可能構成日本存亡危機事態」發言後吃日本料理支持高市早苗是「吃媚日饭」（</span><span class=\"c10 c14\"><a class=\"c9\" href=\"http://www.weibo.com/2656274875/QfB3Zbn09\">央视新闻</a></span><span class=\"c7\">）。</span></li><li class=\"\"><span>11 月份共有 987 則中共文本提及鄭麗文，主要聚焦在鄭麗文在 11 月 1 日就任國民黨黨主席（</span><span class=\"c10 c14\"><a class=\"c9\" href=\"https://www.douyin.com/video/7567587365032611072\">环球时报</a></span><span>）、11 月 8 日出席「50 年代白色恐怖秋祭追思慰靈大會」並祭拜共諜吳石（</span><span class=\"c10 c14\"><a class=\"c9\" href=\"https://taiwan.huanqiu.com/article/4P48YcF8VvK\">環球網</a></span><span>）等事件，以及宣稱鄭麗文接受</span><span class=\"c10\"><a class=\"c9\" href=\"https://asia.nikkei.com/spotlight/policy-asia/taiwan-defense-buildup-can-t-ensure-security-new-kmt-boss-cheng-li-wun\">日經亞洲</a></span><span>在 11 月 14 日發佈的專訪是主張「只有接受一个中国，才能确保台湾生存」（</span><span class=\"c10 c14\"><a class=\"c9\" href=\"https://taiwan.huanqiu.com/article/4P9V3gObhww\">環球網</a></span><span class=\"c7\">）。</span></li><li class=\"\"><span>11 月份共有 724 則中共文本提及沈伯洋，主要聚焦在批評陸委會、民進黨及沈伯洋對於「对台独顽固分子沈伯洋立案侦查」</span><span class=\"c10\"><a class=\"c9\" href=\"http://www.weibo.com/1699432410/QbbBqoKyB\">事件</a></span><span>的回應是「将广大台湾民众与极少数“台独”顽固分子混为一谈」，並宣稱「很多台湾民众与沈伯洋之流划清界限」（</span><span class=\"c10 c14\"><a class=\"c9\" href=\"http://www.taiwan.cn/plzhx/ZBPL/202511/t20251111_12734052.htm\">中国台湾网</a></span><span class=\"c7\">）。</span></li><li class=\"\"><span>11 月份共有 619 則中共文本提及陳之漢（館長），主要聚焦在館長在 11 月 1 日前往天安門廣場觀看中共升國旗、唱國歌而感動（</span><span class=\"c10 c14\"><a class=\"c9\" href=\"https://v.ifeng.com/c/8nvfY8h7alz\">鳳凰網</a></span><span>）、11 月 3 日前往福建「赖氏家庙」替賴清德「寻根」（</span><span class=\"c10 c14\"><a class=\"c9\" href=\"https://www.douyin.com/video/7571625043281628470\">中国台湾网</a></span><span class=\"c7\">）等事件。 </span></li><li class=\"\"><span>11 月份分別有 583 則、465 則中共文本提及陳柏源（閩南狼）及溫子瑜（八炯），主要聚焦在 11 月 13 日福建省公安局宣稱「公安机关悬赏征集台湾网红温子渝、陈柏源违法犯罪线索」事件（</span><span class=\"c10\"><a class=\"c9\" href=\"https://www.hkcna.hk/docDetail.jsp?id=101162053&amp;channel=2805\">香港新聞網</a></span><span class=\"c7\">）。</span></li></ul><div class=\"gdoc-table-container\"><div class=\"table\"><table class=\"c23\"><tbody><tr class=\"c0\"><th class=\"w-2 w-2\" colspan=\"1\" rowspan=\"1\"><p>排序</p></th><th class=\"w-8 w-8\" colspan=\"1\" rowspan=\"1\"><p>人物</p></th><th class=\"w-4 w-4\" colspan=\"1\" rowspan=\"1\"><p>文本數</p></th><th class=\"w-16 w-16\" colspan=\"1\" rowspan=\"1\"><p>身份</p></th></tr><tr class=\"c0\"><td class=\"w-2 number\" colspan=\"1\" rowspan=\"1\"><p>1</p></td><td class=\"w-8\" colspan=\"1\" rowspan=\"1\"><p>賴清德</p></td><td class=\"w-4 number\" colspan=\"1\" rowspan=\"1\"><p>2,578</p></td><td class=\"w-16\" colspan=\"1\" rowspan=\"1\"><p><label class=\"sticker node party dpp\"><span class=\"content\">民進黨</span></label> 現任總統、黨主席</p></td></tr><tr class=\"c0\"><td class=\"w-2 number\" colspan=\"1\" rowspan=\"1\"><p>2</p></td><td class=\"w-8\" colspan=\"1\" rowspan=\"1\"><p>鄭麗文</p></td><td class=\"w-4 number\" colspan=\"1\" rowspan=\"1\"><p>987</p></td><td class=\"w-16\" colspan=\"1\" rowspan=\"1\"><p><label class=\"sticker node party kmt\"><span class=\"content\">國民黨</span></label> 現任黨主席、前立委</p></td></tr><tr class=\"c0\"><td class=\"w-2 number\" colspan=\"1\" rowspan=\"1\"><p>3</p></td><td class=\"w-8\" colspan=\"1\" rowspan=\"1\"><p>沈伯洋</p></td><td class=\"w-4 number\" colspan=\"1\" rowspan=\"1\"><p>724</p></td><td class=\"w-16\" colspan=\"1\" rowspan=\"1\"><p><label class=\"sticker node party dpp\"><span class=\"content\">民進黨</span></label> 現任立委</p></td></tr><tr class=\"c0\"><td class=\"w-2 number\" colspan=\"1\" rowspan=\"1\"><p>4</p></td><td class=\"w-8\" colspan=\"1\" rowspan=\"1\"><p>陳之漢（館長）</p></td><td class=\"w-4 number\" colspan=\"1\" rowspan=\"1\"><p>619</p></td><td class=\"w-16\" colspan=\"1\" rowspan=\"1\"><p>網紅</p></td></tr><tr class=\"c0\"><td class=\"w-2 number\" colspan=\"1\" rowspan=\"1\"><p>5</p></td><td class=\"w-8\" colspan=\"1\" rowspan=\"1\"><p>陳柏源（閩南狼）</p></td><td class=\"w-4 number\" colspan=\"1\" rowspan=\"1\"><p>583</p></td><td class=\"w-16\" colspan=\"1\" rowspan=\"1\"><p>網紅</p></td></tr><tr class=\"c0\"><td class=\"w-2 number\" colspan=\"1\" rowspan=\"1\"><p>6</p></td><td class=\"w-8\" colspan=\"1\" rowspan=\"1\"><p>溫子渝（八炯）</p></td><td class=\"w-4 number\" colspan=\"1\" rowspan=\"1\"><p>465</p></td><td class=\"w-16\" colspan=\"1\" rowspan=\"1\"><p>網紅</p></td></tr><tr class=\"c34\"><td class=\"w-2 number\" colspan=\"1\" rowspan=\"1\"><p>7</p></td><td class=\"w-8\" colspan=\"1\" rowspan=\"1\"><p>洪秀柱</p></td><td class=\"w-4 number\" colspan=\"1\" rowspan=\"1\"><p>363</p></td><td class=\"w-16\" colspan=\"1\" rowspan=\"1\"><p><label class=\"sticker node party kmt\"><span class=\"content\">國民黨</span></label> 前立法院副院長、黨主席</p></td></tr><tr class=\"c34\"><td class=\"w-2 number\" colspan=\"1\" rowspan=\"1\"><p>8</p></td><td class=\"w-8\" colspan=\"1\" rowspan=\"1\"><p>馬英九</p></td><td class=\"w-4 number\" colspan=\"1\" rowspan=\"1\"><p>307</p></td><td class=\"w-16\" colspan=\"1\" rowspan=\"1\"><p><label class=\"sticker node party kmt\"><span class=\"content\">國民黨</span></label> 前總統</p></td></tr><tr class=\"c34\"><td class=\"w-2 number\" colspan=\"1\" rowspan=\"1\"><p>9</p></td><td class=\"w-8\" colspan=\"1\" rowspan=\"1\"><p>郭正亮</p></td><td class=\"w-4 number\" colspan=\"1\" rowspan=\"1\"><p>238</p></td><td class=\"w-16\" colspan=\"1\" rowspan=\"1\"><p>政論名嘴</p></td></tr><tr class=\"c34\"><td class=\"w-2 number\" colspan=\"1\" rowspan=\"1\"><p>10</p></td><td class=\"w-8\" colspan=\"1\" rowspan=\"1\"><p>韓國瑜</p></td><td class=\"w-4 number\" colspan=\"1\" rowspan=\"1\"><p>219</p></td><td class=\"w-16\" colspan=\"1\" rowspan=\"1\"><p><label class=\"sticker node party kmt\"><span class=\"content\">國民黨</span></label> 現任立法院長</p></td></tr><tr class=\"c34\"><td class=\"w-2 number\" colspan=\"1\" rowspan=\"1\"><p>11</p></td><td class=\"w-8\" colspan=\"1\" rowspan=\"1\"><p>黃國昌</p></td><td class=\"w-4 number\" colspan=\"1\" rowspan=\"1\"><p>208</p></td><td class=\"w-16\" colspan=\"1\" rowspan=\"1\"><p><label class=\"sticker node party tpp\"><span class=\"content\">民眾黨</span></label> 現任黨主席</p></td></tr><tr class=\"c34\"><td class=\"w-2 number\" colspan=\"1\" rowspan=\"1\"><p>12</p></td><td class=\"w-8\" colspan=\"1\" rowspan=\"1\"><p>蔡正元</p></td><td class=\"w-4 number\" colspan=\"1\" rowspan=\"1\"><p>173</p></td><td class=\"w-16\" colspan=\"1\" rowspan=\"1\"><p><label class=\"sticker node party kmt\"><span class=\"content\">國民黨</span></label> 前立委、知名政論名嘴</p></td></tr><tr class=\"c34\"><td class=\"w-2 number\" colspan=\"1\" rowspan=\"1\"><p>13</p></td><td class=\"w-8\" colspan=\"1\" rowspan=\"1\"><p>林佳龍</p></td><td class=\"w-4 number\" colspan=\"1\" rowspan=\"1\"><p>170</p></td><td class=\"w-16\" colspan=\"1\" rowspan=\"1\"><p><label class=\"sticker node party dpp\"><span class=\"content\">民進黨</span></label> 現任外交部長</p></td></tr><tr class=\"c0\"><td class=\"w-2 number\" colspan=\"1\" rowspan=\"1\"><p>14</p></td><td class=\"w-8\" colspan=\"1\" rowspan=\"1\"><p>卓榮泰</p></td><td class=\"w-4 number\" colspan=\"1\" rowspan=\"1\"><p>162</p></td><td class=\"w-16\" colspan=\"1\" rowspan=\"1\"><p><label class=\"sticker node party dpp\"><span class=\"content\">民進黨</span></label> 現任行政院長</p></td></tr><tr class=\"c0\"><td class=\"w-2 number\" colspan=\"1\" rowspan=\"1\"><p>15</p></td><td class=\"w-8\" colspan=\"1\" rowspan=\"1\"><p>黃安</p></td><td class=\"w-4 number\" colspan=\"1\" rowspan=\"1\"><p>158</p></td><td class=\"w-16\" colspan=\"1\" rowspan=\"1\"><p>藝人</p></td></tr><tr class=\"c0\"><td class=\"w-2 number\" colspan=\"1\" rowspan=\"1\"><p>16</p></td><td class=\"w-8\" colspan=\"1\" rowspan=\"1\"><p>賴岳謙</p></td><td class=\"w-4 number\" colspan=\"1\" rowspan=\"1\"><p>112</p></td><td class=\"w-16\" colspan=\"1\" rowspan=\"1\"><p>政論名嘴</p></td></tr><tr class=\"c0\"><td class=\"w-2 number\" colspan=\"1\" rowspan=\"1\"><p>17</p></td><td class=\"w-8\" colspan=\"1\" rowspan=\"1\"><p>蔡英文</p></td><td class=\"w-4 number\" colspan=\"1\" rowspan=\"1\"><p>110</p></td><td class=\"w-16\" colspan=\"1\" rowspan=\"1\"><p><label class=\"sticker node party dpp\"><span class=\"content\">民進黨</span></label> 前總統</p></td></tr><tr class=\"c0\"><td class=\"w-2 number\" colspan=\"1\" rowspan=\"1\"><p>18</p></td><td class=\"w-8\" colspan=\"1\" rowspan=\"1\"><p>周錫瑋</p></td><td class=\"w-4 number\" colspan=\"1\" rowspan=\"1\"><p>109</p></td><td class=\"w-16\" colspan=\"1\" rowspan=\"1\"><p><label class=\"sticker node party kmt\"><span class=\"content\">國民黨</span></label> 前台北縣長、政論名嘴</p></td></tr><tr class=\"c0\"><td class=\"w-2 number\" colspan=\"1\" rowspan=\"1\"><p>19</p></td><td class=\"w-8\" colspan=\"1\" rowspan=\"1\"><p>介文汲</p></td><td class=\"w-4 number\" colspan=\"1\" rowspan=\"1\"><p>108</p></td><td class=\"w-16\" colspan=\"1\" rowspan=\"1\"><p>政論名嘴</p></td></tr><tr class=\"c0\"><td class=\"w-2 number\" colspan=\"1\" rowspan=\"1\"><p>20</p></td><td class=\"w-8\" colspan=\"1\" rowspan=\"1\"><p>蕭美琴</p></td><td class=\"w-4 number\" colspan=\"1\" rowspan=\"1\"><p>106</p></td><td class=\"w-16\" colspan=\"1\" rowspan=\"1\"><p><label class=\"sticker node party dpp\"><span class=\"content\">民進黨</span></label> 現任副總統</p></td></tr><tr class=\"c0\"><td class=\"w-2 number\" colspan=\"1\" rowspan=\"1\"><p>20</p></td><td class=\"w-8\" colspan=\"1\" rowspan=\"1\"><p>謝長廷</p></td><td class=\"w-4 number\" colspan=\"1\" rowspan=\"1\"><p>106</p></td><td class=\"w-16\" colspan=\"1\" rowspan=\"1\"><p><label class=\"sticker node party dpp\"><span class=\"content\">民進黨</span></label> 前行政院長、駐日代表、黨主席</p></td></tr><tr class=\"c0\"><td class=\"w-2 number\" colspan=\"1\" rowspan=\"1\"><p>22</p></td><td class=\"w-8\" colspan=\"1\" rowspan=\"1\"><p>王世堅</p></td><td class=\"w-4 number\" colspan=\"1\" rowspan=\"1\"><p>97</p></td><td class=\"w-16\" colspan=\"1\" rowspan=\"1\"><p><label class=\"sticker node party dpp\"><span class=\"content\">民進黨</span></label> 現任立委</p></td></tr><tr class=\"c0\"><td class=\"w-2 number\" colspan=\"1\" rowspan=\"1\"><p>23</p></td><td class=\"w-8\" colspan=\"1\" rowspan=\"1\"><p>邱毅</p></td><td class=\"w-4 number\" colspan=\"1\" rowspan=\"1\"><p>95</p></td><td class=\"w-16\" colspan=\"1\" rowspan=\"1\"><p>政論名嘴</p></td></tr><tr class=\"c0\"><td class=\"w-2 number\" colspan=\"1\" rowspan=\"1\"><p>24</p></td><td class=\"w-8\" colspan=\"1\" rowspan=\"1\"><p>王炳忠</p></td><td class=\"w-4 number\" colspan=\"1\" rowspan=\"1\"><p>89</p></td><td class=\"w-16\" colspan=\"1\" rowspan=\"1\"><p><label class=\"sticker node party np\"><span class=\"content\">新黨</span></label> 前發言人</p></td></tr><tr class=\"c0\"><td class=\"w-2 number\" colspan=\"1\" rowspan=\"1\"><p>25</p></td><td class=\"w-8\" colspan=\"1\" rowspan=\"1\"><p>呂禮詩</p></td><td class=\"w-4 number\" colspan=\"1\" rowspan=\"1\"><p>84</p></td><td class=\"w-16\" colspan=\"1\" rowspan=\"1\"><p>政論名嘴</p></td></tr></tbody></table></div><p class=\"c4 description\" id=\"h.itkr4aaqybma\"><span class=\"c24\">2025 年 11 月中共官媒跨平台帳號提及台灣政治人物及名嘴列表，人物次序依提及中共文本數降冪排列。資料來源：IORG 資料庫；台灣資訊環境研究中心 IORG 製表。</span></p></div><div class=\"separator\"></div><div class=\"stickers\"></div><h2 class=\"c4\" id=\"h2-3\"><span class=\"c26\">精選時事</span></h2><h3 class=\"c4\" id=\"h.i8eyq99aax3i\"><span class=\"c29\">高市早苗「存立危機事態」發言：「粗暴干涉中国内政」、「向“台独”分裂势力释放错误信号」，暴露日本「右翼势力突破军事束缚危险野心」、「军国主义余毒」、「破坏地区和平」，「疯狂言论引发多位台、日政要及专家痛批」；賴清德吃日本料理是「吃媚日饭」、「认贼作父」</span></h3><ul class=\"\"><li class=\"\"><span class=\"c7\">11 月份共有 4,531 則相關文本，佔比 12.6%。</span></li><li class=\"\"><span>11 月 7 日，<label class=\"sticker node group\"><span class=\"content\">中央社</span></label> </span><span class=\"c10\"><a class=\"c9\" href=\"https://www.cna.com.tw/news/aopl/202511070202.aspx\">中央社</a></span><span class=\"c7\">發布報導「高市早苗：台灣有事可能構成日本存亡危機事態 能行使集體自衛權」：日本首相高市早苗今天在眾議院接受質詢時表示，如果「台灣有事」（發生緊急狀況）伴隨對方使用武力的情況，有可能構成安全保障法制中，日本能夠行使集體自衛權的「存亡危機事態」，不過仍要看實際發生的個別具體情況。</span></li><li class=\"\"><span>11 月 9 日，現 <label class=\"sticker node group\"><span class=\"content\">🇨🇳 人民日报</span></label>「环球时报」特約評論員</span><span class=\"c10\"><a class=\"c9\" href=\"https://www.weibo.com/1989660417/QcXc683hA\">胡锡进</a></span><span class=\"c7\">發布微博：「如果中国实现统一对日本意味着“关乎生存的危机”，那可麻烦了。因为中国肯定会统一，我想届时还是让高市早苗带着一些日本的狂妄之徒“停止生存”吧」。</span></li><li class=\"\"><span>11 月 10 日，<label class=\"sticker node group\"><span class=\"content\">🇨🇳 人民日报</span></label>「</span><span class=\"c10\"><a class=\"c9\" href=\"https://taiwan.huanqiu.com/article/4P5S6Zd8TWC\">环球网</a></span><span>」發表作者「北平锋」的文章「决不容许任何外部势力插手台湾问题」，內文宣稱高市的發言是對「中国内政的粗暴干涉」、「轮不到外部势力说三道四、指手画脚」、「向“台独”分裂势力释放了严重的错误信号，极易加剧台海地区的紧张局势」、「本质上是在为“台独”分裂势力站台，无疑会让“台独”分裂势力产生误判，进一步冒险挑衅，会严重损害两岸同胞的根本利益」，並引用日本前首相</span><span class=\"c10\"><a class=\"c9\" href=\"https://x.com/hatoyamayukio/status/1986998583552622810?s=46&amp;t=hIn9fWEPZlUWJnsqOlsezg\">鳩山由紀夫</a></span><span>、</span><span class=\"c10\"><a class=\"c9\" href=\"https://tchina.kyodonews.net/news/2025/11/69be8dcf6297.html?phrase=%E9%87%8E%E7%94%B0%E4%BD%B3%E5%BD%A5&amp;words=%E9%87%8E%E7%94%B0,%E4%BD%B3,%E5%BD%A5\">野田佳彥</a></span><span class=\"c7\">的觀點，認為高市早苗的發言「危險」。</span></li><li class=\"\"><span>11 月 12 日，<label class=\"sticker node group\"><span class=\"content\">🇨🇳 国台办</span></label>「</span><span class=\"c10\"><a class=\"c9\" href=\"http://www.taiwan.cn/plzhx/plyzl/202511/t20251112_12734316.htm\">中国台湾网</a></span><span class=\"c7\">」發布作者「郭大路」的文章「妄图在台湾问题上玩火？高市早苗的狂言只会引火自焚！」，內文宣稱高市的發言是「粗暴干涉中国内政，充分暴露了日本右翼势力妄图借台海问题突破军事束缚的危险野心」、「忘战必危，好战必亡。高市早苗的恶劣行径是在将日本拖入冲突泥潭，让日本沦为地区和平的破坏者」，亦引用鳩山由紀夫、野田佳彥等人發言宣稱「高市早苗的上述疯狂言论已经引发多位日本前政要、专家和其国内媒体痛批」。</span></li><li class=\"\"><span>11 月 17 日，<label class=\"sticker node group\"><span class=\"content\">🇨🇳 广电总台</span></label>「</span><span class=\"c10\"><a class=\"c9\" href=\"https://www.itaiwannews.cn/2025-11-17/19ec78a9-8c3f-bdc3-d182-63bc684378ab.html\">海峡飞虹</a></span><span class=\"c7\">」發布文本「高市早苗涉台恶劣言论的狼子野心值得高度警惕」，內文宣稱高市的發言「已引发周边国家的强烈反应，受到俄罗斯、韩国等国家的公开批评 [⋯] 也引起包括台湾同胞在内的两岸中国人的极大愤慨」，並引用前總統馬英九的評論「两岸问题不能假手外国介入、两岸的中国人有智慧解决分歧」、前國民黨主席洪秀柱的評論「裸裸的历史傲慢与政治干涉」、<label class=\"sticker node group\"><span class=\"content\">旺中</span></label> 副董事長周錫瑋的評論「没那个实力还要讲大话，小孩子玩大车会出车祸的」。</span></li><li class=\"\"><span>11 月 17 日，<label class=\"sticker node group\"><span class=\"content\">🇨🇳 新华社</span></label>「</span><span class=\"c10\"><a class=\"c9\" href=\"http://www.news.cn/world/20251117/131099cf671442159e5087640cbce211/c.html\">新华网</a></span><span class=\"c7\">」發布文本「在台湾问题上生事，就是给自己找事」，內文宣稱日本統治台灣時期「是台湾历史最黑暗的一页」、「日本右翼政客与“台独”势力暗通款曲 [⋯] 图谋利用台湾作为地缘博弈“战略支点” [...] 颠覆日本作为战败国的战后国际秩序」，並以來源不明的「台湾社会各界」批評日本「“不负责任”的言论是在恶意挑拨两岸对立对抗、加剧台海紧张局势，尽显日本右翼政客毫无历史良知」。</span></li><li class=\"\"><span>11 月 21 日，<label class=\"sticker node group\"><span class=\"content\">🇨🇳 中共中央军委</span></label>「</span><span class=\"c10\"><a class=\"c9\" href=\"http://www.mod.gov.cn/gfbw/jmsd/16423062.html\">解放军报</a></span><span class=\"c7\">」發布文本「钧声丨所谓“存亡危机”暗藏军国主义余毒」，內文宣稱高市的發言「完全暴露了日本军国主义余毒未消的本质」、「日本国内军国主义阴魂不散、死灰复燃的现实表现」、「一旦把军国主义战争怪兽释放出来，必将置日本于万劫不复之地」。</span></li><li class=\"\"><span>11 月 26 日，<label class=\"sticker node group\"><span class=\"content\">🇨🇳 国台办</span></label>「</span><span class=\"c10\"><a class=\"c9\" href=\"http://www.gwytb.gov.cn/xwdt/xwfb/wyly/202511/t20251126_12737224.htm\">国台办</a></span><span class=\"c7\">」發布文本「国台办：赖清德吃媚日饭，干卖台勾当」，內文包含「国务院台办发言人彭庆恩应询表示，高市早苗的涉台错误言论粗暴干涉中国内政，严重违反国际法和国际关系基本准则，严重破坏战后国际秩序，严重违背一个中国原则和中日四个政治文件精神，严重伤害中国人民感情。日方应立即反思纠错，收回涉台错误言论 [⋯] 彭庆恩表示，赖清德吃的是媚日的饭，干的是卖台的勾当。其言其行令人作呕，让世人再度看清其数典忘祖、背叛民族的丑恶嘴脸。正告赖清德当局，凡是倚仗外部势力的行径必将自取其辱，凡是背叛民族的罪人必遭正义审判」。</span></li><li class=\"\"><span>11 月 29 日，<label class=\"sticker node group\"><span class=\"content\">🇨🇳 人民日报</span></label>「</span><span class=\"c10\"><a class=\"c9\" href=\"https://taiwan.huanqiu.com/article/4PLAb3V2pm2\">环球网</a></span><span class=\"c7\">」發布作者「北平锋」的文章「赖清德恋殖媚日是在助日复活军国主义」，內文宣稱「赖清德吃日本寿司、高喊“挺日”，暴露其殖民心态深入骨髓且外化于行。其所谓“外交”，不过是在向昔日殖民者摇尾乞怜」、「战后的日本，从未真正清算军国主义遗毒，日本靖国神社年年鬼火不断，历史教科书屡遭篡改，自卫队扩编为“国防军”铺路。赖清德对这些视而不见，反而逢人便鼓吹“台日命运共同体”。他刻意淡化日本当年对台湾的殖民统治罪行，有意忽略其强征慰安妇、推行皇民化、剥夺母语、残暴镇压抗日志士的血腥历史，这是认贼作父」。</span></li></ul><div class=\"separator\"></div><div class=\"stickers\"></div><h2 class=\"c4\" id=\"h2-4\"><span class=\"c26\">精選影劇</span></h2><h3 class=\"c4\" id=\"h.x983h4rmtb7\"><span>紀錄片「国土重光」</span><span class=\"c29\">：由国台办、全国台湾同胞联谊会、央视总台聯合攝製，紀念台灣光復 80 週年，糾正台獨史觀，展現台灣少數民族起源於長江流域的考古學成果</span></h3><ul class=\"\"><li class=\"\"><span class=\"c7\">11 月份共有 55 則相關文本，佔比 0.015%。</span></li><li class=\"\"><span>11 月 1 日，<label class=\"sticker node group\"><span class=\"content\">🇨🇳 广电总台</span></label>「</span><span class=\"c10\"><a class=\"c9\" href=\"http://www.weibo.com/2039753857/QbMVqdSVE\">CCTV</a></span><span>」發布微博，內文包含「为纪念台湾光复80周年，</span><span class=\"c37\">由中共中央台湾工作办公室、中华全国台湾同胞联谊会与中央广播电视总台联合摄制</span><span>，总台华语环球节目中心承制的 6 集纪录片《国土重光—纪念台湾光复 80 周年》将于 11 月 1 日起在综合频道（CCTV-1）、中文国际频道（CCTV-4）播出，敬请收看！」。6 集影片在 <label class=\"sticker node group\"><span class=\"content\">🇨🇳 广电总台</span></label>「</span><span class=\"c10\"><a class=\"c9\" href=\"https://www.youtube.com/@CCTVDocumentary\">CCTV纪录</a></span><span class=\"c7\">」 YouTube 頻道之影片連結、所有受訪者及身份詳見下表。</span></li><li class=\"\"><span>11 月 5 日，<label class=\"sticker node group\"><span class=\"content\">🇨🇳 国台办</span></label>「</span><span class=\"c10\"><a class=\"c9\" href=\"http://www.gwytb.gov.cn/xwdt/xwfb/wyly/202511/t20251105_12732703.htm\">国台办</a></span><span class=\"c7\">」發布文本「国台办：纪录片《国土重光——纪念台湾光复80周年》是对“台独”史观的有力纠正」，內文包含「国务院台办发言人张晗应询表示 [⋯] 这是一部思想性与故事性兼具的电视精品，两岸很多朋友观看后表示，该片严谨性、学术性、理论性很高，既捍卫了台湾光复正史，也是对“台独”史观的有力纠正」。</span></li><li class=\"\"><span>11 月 6 日，<label class=\"sticker node group\"><span class=\"content\">🇨🇳 广电总台</span></label>「</span><span class=\"c10\"><a class=\"c9\" href=\"https://www.weibo.com/u/3266943013\">央视网</a></span><span class=\"c7\">」發布微博，內文包含「6 集纪录片《国土重光——纪念台湾光复 80 周年》播出以来，受到舆论广泛关注，在网络上热度颇高」、「长期研究两岸关系的钟厚涛对记者说，该片内容超出了普通的纪录片，有高度的文献价值，例如展现了台湾少数民族起源于长江流域，与大陆的民族和族群同根同源的最新考古学成果」。</span></li></ul><div class=\"gdoc-table-container\"><div class=\"table\"><table class=\"c23\"><tbody><tr class=\"c0\"><th class=\"w-12 w-12\" colspan=\"1\" rowspan=\"1\"><p>標題</p></th><th class=\"w-4 w-4\" colspan=\"1\" rowspan=\"1\"><p>影片時長</p></th><th class=\"w-20 w-20\" colspan=\"1\" rowspan=\"1\"><p>受訪者</p></th></tr><tr class=\"c0\"><td class=\"w-12\" colspan=\"1\" rowspan=\"1\"><p class=\"c5 c11\"><span class=\"c2\"><a class=\"c9\" href=\"https://www.youtube.com/watch?v=mNt9FgLTmHs&amp;list=PLwXMmy5fUrVwzTzSBR0Z__nzLsitps9rV&amp;index=7\">01 甲午之殇</a></span><span class=\"c1\">：一本日记揭露日本从150多年前就觊觎台湾</span></p></td><td class=\"w-4\" colspan=\"1\" rowspan=\"1\"><p>26:59</p></td><td class=\"w-20\" colspan=\"1\" rowspan=\"1\"><ul class=\"\"><li class=\"\"><span class=\"c1\">汪毅夫（台湾问题专家）</span></li><li class=\"\"><span class=\"c1\">王传超（復旦大学教授）</span></li><li class=\"\"><span class=\"c1\">刘孔昭（厦门大学台湾研究院原副院长）</span></li><li class=\"\"><span class=\"c1\">戚嘉林（統一聯盟黨榮譽主席）</span></li><li class=\"\"><span class=\"c1\">古英勇（排灣族長老）</span></li><li class=\"\"><span class=\"c1\">陈思（厦门大学台湾研究院副教授）</span></li><li class=\"\"><span class=\"c1\">纐纈厚（日本山口大學名譽教授）</span></li><li class=\"\"><span class=\"c1\">翁飞（安徽省文史研究馆馆员）</span></li><li class=\"\"><span class=\"c1\">马骏杰（中国甲午战争博物馆首席专家）</span></li></ul></td></tr><tr class=\"c0\"><td class=\"w-12\" colspan=\"1\" rowspan=\"1\"><p class=\"c5 c11\"><span class=\"c2\">02 </span><span class=\"c2\"><a class=\"c9\" href=\"https://www.youtube.com/watch?v=XwQMKTvAg0g&amp;list=PLwXMmy5fUrVwzTzSBR0Z__nzLsitps9rV&amp;index=6\">誓死保台</a></span><span class=\"c1\">：爱国清军联合全台民间力量迅速集结 英勇御敌 坚持约5个多月 反抗日本侵略者</span></p></td><td class=\"w-4\" colspan=\"1\" rowspan=\"1\"><p>26:59</p></td><td class=\"w-20\" colspan=\"1\" rowspan=\"1\"><ul class=\"\"><li class=\"\"><span class=\"c1\">丘志斌（丘逢甲曾孙）</span></li><li class=\"\"><span class=\"c1\">纐纈厚（日本山口大學名譽教授）</span></li><li class=\"\"><span class=\"c1\">姜文滉（抗日人士姜紹祖曾孫）</span></li><li class=\"\"><span class=\"c1\">丘秀芷（丘逢甲姪孙女）</span></li><li class=\"\"><span class=\"c1\">刘先慧（刘永福玄孙女）</span></li><li class=\"\"><span class=\"c1\">黃人山（文史工作者）</span></li><li class=\"\"><span class=\"c1\">褚静涛（中国社会科学近代史研究所研究员）</span></li><li class=\"\"><span class=\"c1\">湯錦台（文史工作者）</span></li><li class=\"\"><span class=\"c1\">鄭道聰（文史工作者）</span></li><li class=\"\"><span class=\"c1\">刘孔昭（厦门大学台湾研究院原副院长）</span></li><li class=\"\"><span class=\"c1\">杨毅周（中华全国台湾同胞连议会副会长）</span></li><li class=\"\"><span class=\"c1\">孫若怡（中興大學歷史系退休教授）</span></li></ul></td></tr><tr class=\"c0\"><td class=\"w-12\" colspan=\"1\" rowspan=\"1\"><p class=\"c5 c11\"><span class=\"c2\"><a class=\"c9\" href=\"https://www.youtube.com/watch?v=b4pmpm3u1zY&amp;list=PLwXMmy5fUrVwzTzSBR0Z__nzLsitps9rV&amp;index=5\">03 不屈抗争</a></span><span class=\"c1\">：80多年前台湾同胞掀起恢复中国国籍的热潮 17岁少年目睹日本强占台湾决心撰写台湾通史</span></p></td><td class=\"w-4\" colspan=\"1\" rowspan=\"1\"><p>26:59</p></td><td class=\"w-20\" colspan=\"1\" rowspan=\"1\"><ul class=\"\"><li class=\"\"><span class=\"c1\">連勝文（中國國民黨前副主席、連橫曾孫）</span></li><li class=\"\"><span class=\"c1\">汪毅夫（台湾问题专家）</span></li><li class=\"\"><span class=\"c1\">楊渡（前中華文化總會秘書長）</span></li><li class=\"\"><span class=\"c1\">羅秋昭（羅福星孫女）</span></li><li class=\"\"><span class=\"c1\">林真（福建省档案馆原副馆长）</span></li><li class=\"\"><span class=\"c1\">杨毅周（中华全国台湾同胞连议会副会长）</span></li><li class=\"\"><span class=\"c1\">瑪姮巴丸（莫那魯道曾孫女）</span></li><li class=\"\"><span class=\"c1\">孫若怡（中興大學歷史系退休教授）</span></li><li class=\"\"><span class=\"c1\">高金素梅（現任立委）</span></li></ul></td></tr><tr class=\"c0\"><td class=\"w-12\" colspan=\"1\" rowspan=\"1\"><p class=\"c5 c11\"><span class=\"c2\"><a class=\"c9\" href=\"https://www.youtube.com/watch?v=n08v9OznaFA&amp;list=PLwXMmy5fUrVwzTzSBR0Z__nzLsitps9rV&amp;index=4\">04 山海同袍</a></span><span class=\"c1\">：抗战时期台湾的真实历史影像 93岁台湾少年团团员亲述抗日宣传热烈情景</span></p></td><td class=\"w-4\" colspan=\"1\" rowspan=\"1\"><p>26:59</p></td><td class=\"w-20\" colspan=\"1\" rowspan=\"1\"><ul class=\"\"><li class=\"\"><span class=\"c25\">蕭開平</span><span class=\"c1\">（蕭道應之子）</span></li><li class=\"\"><span class=\"c1\">张海鹏（中国社会科学院学部委员）</span></li><li class=\"\"><span class=\"c1\">徐博东（北京联合大学台湾研究院创院院长）</span></li><li class=\"\"><span class=\"c1\">李力群（李友邦之子）</span></li><li class=\"\"><span class=\"c1\">楊維真（中正大學歷史系教授）</span></li><li class=\"\"><span class=\"c1\">劉惠敏（台灣義勇少年團團員）</span></li><li class=\"\"><span class=\"c1\">柯偉林（哈佛大學費正清中國研究中心原主任）</span></li><li class=\"\"><span class=\"c1\">林為民（林正亨之子）</span></li></ul></td></tr><tr class=\"c0\"><td class=\"w-12\" colspan=\"1\" rowspan=\"1\"><p class=\"c5 c11\"><span class=\"c2\"><a class=\"c9\" href=\"https://www.youtube.com/watch?v=_lrNuKi8gQ8&amp;list=PLwXMmy5fUrVwzTzSBR0Z__nzLsitps9rV&amp;index=3\">05 破晓曙光</a></span><span class=\"c1\">：《开罗宣言》是确认台湾属于中国领土的第一份国际性文件</span></p></td><td class=\"w-4\" colspan=\"1\" rowspan=\"1\"><p>26:59</p></td><td class=\"w-20\" colspan=\"1\" rowspan=\"1\"><ul class=\"\"><li class=\"\"><span class=\"c1\">索拉布・古普塔（美國中美研究中心高級研究員）</span></li><li class=\"\"><span class=\"c1\">徐康（重庆红岩革命历史博物馆研究馆员）</span></li><li class=\"\"><span class=\"c1\">楊維真（中正大學歷史系教授）</span></li><li class=\"\"><span class=\"c1\">連惠心（連橫曾孫女）</span></li><li class=\"\"><span class=\"c1\">褚静涛（中国社会科学近代史研究所研究员）</span></li><li class=\"\"><span class=\"c1\">余尔望（余氏家族后人）</span></li><li class=\"\"><span class=\"c1\">謝孟雄（謝東閔之子）</span></li><li class=\"\"><span class=\"c1\">柯偉林（哈佛大學費正清中國研究中心原主任）</span></li><li class=\"\"><span class=\"c1\">张海鹏（中国社会科学院学部委员）</span></li></ul></td></tr><tr class=\"c0\"><td class=\"w-12\" colspan=\"1\" rowspan=\"1\"><p class=\"c5 c11\"><span class=\"c2\"><a class=\"c9\" href=\"https://www.youtube.com/watch?v=-OI45pjL5aQ&amp;list=PLwXMmy5fUrVwzTzSBR0Z__nzLsitps9rV&amp;index=2\">06 回归祖国</a></span><span class=\"c1\">：亲历者回忆台湾光复时的盛况 各地的市民们涌上街狂欢</span></p></td><td class=\"w-4\" colspan=\"1\" rowspan=\"1\"><p>26:59</p></td><td class=\"w-20\" colspan=\"1\" rowspan=\"1\"><ul class=\"\"><li class=\"\"><span class=\"c1\">林光輝（林獻堂侄孫）</span></li><li class=\"\"><span class=\"c1\">楊渡（前中華文化總會秘書長）</span></li><li class=\"\"><span class=\"c1\">陳萬中（陳頤鼎之子）</span></li><li class=\"\"><span class=\"c1\">柯偉林（哈佛大學費正清中國研究中心原主任）</span></li><li class=\"\"><span class=\"c1\">康欣（国际时事评论员）</span></li><li class=\"\"><span class=\"c1\">盧秀月（台灣光復親歷者） </span></li><li class=\"\"><span class=\"c1\">戚嘉林（統一聯盟黨榮譽主席）</span></li><li class=\"\"><span class=\"c1\">藍博洲（作家）</span></li><li class=\"\"><span class=\"c1\">李正倫（李建興之孫）</span></li></ul></td></tr></tbody></table></div><p class=\"c4 description\" id=\"h.lvfycy6i4l5b\"><span class=\"c24\">中共紀錄片「国土重光」6 集標題、時長、受訪者列表。人物排序按影片出現次序排列。台灣資訊環境研究中心 IORG 製表。</span></p></div><h3 class=\"c4\" id=\"h.33r4h6h6wqv\"><span class=\"c29\">賽德克巴萊：「中国台湾抗日史诗电影」在 12 月上映，「中国台湾青年」莫那鲁道率領同胞英勇抵抗日軍入侵，電影代表不能忘記「中国台湾」血性抗日傳奇，也是對「台灣是中國不可分割一部分」的生動印證</span></h3><ul class=\"\"><li class=\"\"><span class=\"c7\">11 月份共有 72 則相關文本，佔比 0.02%。</span></li><li class=\"\"><span>11 月 12 日，<label class=\"sticker node group\"><span class=\"content\">🇨🇳 厦门广电</span></label>「</span><span class=\"c10\"><a class=\"c9\" href=\"https://www.youtube.com/watch?v=1OW1GslYOqA\">天天看一廈</a></span><span class=\"c7\">」發布 YT Shorts，影片說明文字包含「11月11日，台灣知名導演魏德聖攜代表作《賽德克·巴萊》亮相廈門金雞影展，分享電影的創作心路歷程。談及當年為籌拍影片借錢的經歷時候，他直言 “只要你想得到，就一定可以被完成”」。</span></li><li class=\"\"><span>11 月 26 日，<label class=\"sticker node group\"><span class=\"content\">🇨🇳 上海报业集团</span></label>「</span><span class=\"c10\"><a class=\"c9\" href=\"https://www.thepaper.cn//newsDetail_forward_32045814\">澎湃新聞</a></span><span class=\"c7\">」發布文本「《赛德克·巴莱》上下部官宣中国大陆上映，定档12月12、13日」，內文包含「由魏德圣执导的中国台湾抗日史诗电影《赛德克·巴莱》上下部发布定档预告及海报，官宣中国大陆上映」、「定档预告一开篇就揭露日本侵略中国台湾，中国台湾人誓死抵抗 [⋯] 展现中国台湾民众反抗日寇侵略的坚定决心」 、「以日本侵略中国台湾时期为背景，骁勇善战的中国台湾青年莫那鲁道，率领同胞英勇抵抗日军入侵。面对日军的资源掠夺，他们凭借山林地势殊死搏斗，让侵略者付出惨痛代价」。</span></li><li class=\"\"><span>11 月 26 日，<label class=\"sticker node group\"><span class=\"content\">🇨🇳 国务院</span></label>「</span><span class=\"c10\"><a class=\"c9\" href=\"https://www.weibo.com/3164957712/QfB85hBKe\">中国网</a></span><span>」發布微博，內文包含「#电影赛德克巴莱上下部定档#改编自中国台湾真实抗日历史」、「影片以真实历史为骨、以血性为魂，呈现中国台湾人民不甘受辱、反杀日寇的血性故事，成为年度最值得致敬、最具精神冲击力的国民级作品。勿忘国耻，致敬先辈！值此台湾光复 80 周年之际，</span><span>豆瓣 8.9 分双部高分硬核品质的华语影史血性尊严丰碑</span><span class=\"c7\">首次以上下部的形式登陆中国大陆大银幕」、「不能忘记的中国台湾血性抗日传奇」。</span></li><li class=\"\"><span>11 月 27 日，<label class=\"sticker node group\"><span class=\"content\">🇨🇳 国务院</span></label>「</span><span class=\"c10\"><a class=\"c9\" href=\"http://www.hkcna.hk/docDetail.jsp?id=101174999&amp;channel=2805\">香港新聞網</a></span><span class=\"c7\">」發布文本「台灣電影《賽德克·巴萊》將在大陸重映，引發台各界關注」，內文包含「在中日關係因日本首相高市早苗發表涉台錯誤言論而變得緊張之際，大陸將重映台灣電影《賽德克·巴萊》，引發台各界的關注」、「在此背景下，《賽德克・巴萊》的重映更具現實意義，大陸方面多次援引《開羅宣言》等歷史文件重申對台主權，而影片所展現的台灣同胞反抗日本殖民統治的歷史事實，正是對“台灣是中國不可分割一部分”的生動印證，也對任何企圖干涉中國內政的勢力形成有力回應」。</span></li></ul><div class=\"separator\"></div><div class=\"stickers\"></div><h2 class=\"c4\" id=\"h2-5\"><span>精選科技</span></h2><h3 class=\"c4\" id=\"h.bjtrpkfvhcqk\"><span class=\"c29\">吉林一号卫星：公布多張台灣高清衛星影像是「家的俯瞰」，讓台獨無所遁形、恐慌，「岛内舆论」關注的是衛星的「硬实力强、清晰度高、震慑力大」</span></h3><ul class=\"\"><li class=\"\"><span class=\"c7\">11 月份共有 213 則相關文本，佔比 0.59%。</span></li><li class=\"\"><span>11 月 2 日，<label class=\"sticker node group\"><span class=\"content\">🇨🇳 鳳凰衛視</span></label>「</span><span class=\"c10\"><a class=\"c9\" href=\"https://news.ifeng.com/c/8nxNbKkpaNL\">鳳凰網</a></span><span class=\"c7\">」發布文本「“吉林一号”回应俯瞰台湾：我们想拍哪里，就能拍到哪里」，內文包含「今年 10 月 25 日，在首个台湾光复纪念日之际，“吉林一号”公布了多张台湾高清卫星影像 [⋯] 日月潭“日轮”与“月钩”的形态，阿里山大片绵延起伏的森林，台北市的城市脉络与道路网格，台北港营运码头的集装箱，中正纪念堂两厅院的屋顶，鹅銮鼻半岛鲜明海岸线和白色灯塔，以及台湾半导体产业核心新竹科学园区密集的厂房建筑等都清晰可见」、「岛内舆论表示，中国科技发展令人惊叹 [⋯] 国防部新闻发言人张晓刚表示，中国的卫星看看中国的大好河山很正常，没有什么可大惊小怪的」。</span></li><li class=\"\"><span>11 月 3 日，<label class=\"sticker node group\"><span class=\"content\">🇨🇳 北京广播电视台</span></label>「</span><span class=\"c10\"><a class=\"c9\" href=\"https://www.weibo.com/1893892941/QcaE06SqW\">北京日报</a></span><span>」發布微博，內文包含「#吉林一号让台独战时无所遁形# #吉林一号照片让台独感到恐慌#」、「海峡两岸关系研究中心特约研究员郑剑介绍：“如此高解析度的卫星照片，居然是民用卫星，解放军的军用侦察卫星它会达到多少？」、「“将来如果不幸以非和平方式解决台湾问题的时候，你的每一寸土地、每一个目标、每一个点位，大陆方面都是清清楚楚的，战时你无所遁形”」。同日，<label class=\"sticker node group\"><span class=\"content\">🇨🇳 北京广播电视台</span></label>「</span><span class=\"c10 c14\"><a class=\"c9\" href=\"http://www.weibo.com/1697601814/QcaL8CNZq\">长安街知事</a></span><span>」、「</span><span class=\"c10 c14\"><a class=\"c9\" href=\"http://www.weibo.com/1703371307/QcaMBaU0Q\">北京晚报</a></span><span>」、「</span><span class=\"c10 c14\"><a class=\"c9\" href=\"http://www.weibo.com/2145917613/QcaMK2QtK\">北京日报都视频</a></span><span>」、「</span><span class=\"c10 c14\"><a class=\"c9\" href=\"http://www.weibo.com/1617264814/QcaMK1JWV\">京报网_北京日报官方网站</a></span><span class=\"c7\">」發布相同內容微博。</span></li><li class=\"\"><span>11 月 5 日，<label class=\"sticker node group\"><span class=\"content\">🇨🇳 国台办</span></label>「</span><span class=\"c10\"><a class=\"c9\" href=\"http://www.taiwan.cn/xwzx/xwfbh/gtbxwfbh/fbhwb/202511/t20251105_12732667.htm\">中国台湾网</a></span><span>」發布文本「国台办 2025 年 11 月 5 日新闻发布会文字实录」，針對「中央广播电视总台“看台海”和“日月谭天”新媒体记者：大陆商用卫星“吉林一号”日前公布了 8 张太空视角下涵盖台湾各地的卫星影像图片，引发两岸网友关注和热议，有不少台湾网友在卫星图里找自己家房子。有岛内舆论指出，这展示了大陆卫星技术实力及对祖国完全统一的坚定信心。对此有何评论？」，國台辦發言人張晗回應「台湾是祖国的宝岛。随着大陆科技水平的持续提升，我们丈量国土更精准，守护家园更坚实，拥抱未来更笃定。正如网友所言，这是“家的俯瞰”。不论是巍峨的万里长城，还是秀美的日月潭；不论是高楼林立的上海，还是繁忙的台北港，都是祖国的锦绣河山，都是中华民族的美好家园。我们诚挚欢迎更多台湾同胞来大陆走走看看，饱览大好河山，见证神州风貌，感受家的温暖」。同日，<label class=\"sticker node group\"><span class=\"content\">🇨🇳 人民日报</span></label>「</span><span class=\"c10\"><a class=\"c9\" href=\"https://www.weibo.com/2803301701/QcptT12Lx\">人民日报</a></span><span>」、<label class=\"sticker node group\"><span class=\"content\">🇨🇳 广电总台</span></label>「</span><span class=\"c10\"><a class=\"c9\" href=\"https://www.weibo.com/2039753857/QcptKcplZ\">CCTV 4</a></span><span>」、<label class=\"sticker node group\"><span class=\"content\">🇨🇳 国务院</span></label>「</span><span class=\"c10 c14\"><a class=\"c9\" href=\"http://www.weibo.com/1686785965/Qcps98BuU\">环球时报-英文版</a></span><span class=\"c7\">」等中央層級官媒發布微博，內容包含國台辦發言人張晗在記者會上的發言內容。</span></li><li class=\"\"><span>11 月 8 日，<label class=\"sticker node group\"><span class=\"content\">🇨🇳 人民日报</span></label>「</span><span class=\"c10\"><a class=\"c9\" href=\"https://taiwan.huanqiu.com/article/4P3RBVisWu3\">环球网</a></span><span class=\"c7\">」發布作者「日月谭天」的文章「日月谭天 | 从大陆卫星拍到的台湾影像中，岛内看到了什么？」，內文包含「连日来，台湾媒体跟进报道相关消息，政论节目围绕政治、军事等方面意涵展开解读，许多岛内网友留言赞叹大陆科技先进，有的还在卫星图中找起了自家的房子。谭主梳理发现，岛内对“吉林一号”的关注点主要集中在以下三个方面」、「一是硬实力强，多家岛内媒体以“把台湾看光光的大陆卫星‘吉林一号’来头曝光”为题，引述总台“看台海”报道称，截至今年 10 月 11 日，“吉林一号”已完成第 31 次发射，在轨卫星数量增至 141 颗，成为全球最大的亚米级商业遥感卫星星座，形成强大对地观测能力」、「二是清晰度高，台军退役将领张延廷在政论节目中表示，如今电子光学设备被安装在低轨人造卫星上，清晰度已进入“以厘米为单位”的层级，过去放大后会模糊的细节，现在都能看得很清楚，“不要说道路，连巷子都可以看到”」、「三是震慑力大，台湾时事评论员谢寒冰在岛内节目中指出，大陆光是一个商用卫星就已经把台湾看得清清楚楚，军用卫星的精度应该更高。台湾网红“馆长”陈之汉在大陆参访时看到图片，感叹大陆卫星发达，强调台湾没有能力打仗，台湾人民也不要打仗。岛内网友的留言更直接：“一览无遗，无所遁形”“卫星影像越清晰，‘斩首’行动就越精准”“释放出这些讯息，是在警告‘台独’势力”」。</span></li></ul><h3 class=\"c4\" id=\"h.otm1q1sevya1\"><span class=\"c29\">高德导航：「台湾省」終於可以用了，每一寸土地都清清楚楚，「岛内名嘴」認為比 Google 地圖還要好，讓某些人「破防」</span></h3><ul class=\"\"><li class=\"\"><span class=\"c7\">11 月份共有 163 則相關文本，佔比 0.45%。</span></li><li class=\"\"><span>11 月 2 日，<label class=\"sticker node group\"><span class=\"content\">🇨🇳 北京广播电视台</span></label>「</span><span class=\"c10\"><a class=\"c9\" href=\"https://www.douyin.com/video/7567985591309077775\">北京日报</a></span><span>」發布抖音，標題為「【台湾歌手、主持人黄安发文称：“一觉醒来，导航都变了！#台湾省可以使用高德导航啦 ！”】（黄安、人民日报）」，影片內容引用藝人黃安在 11 月 1 日發布的</span><span class=\"c10\"><a class=\"c9\" href=\"https://www.weibo.com/2489313225/QbNDzF6zF\">微博</a></span><span class=\"c7\">。</span></li><li class=\"\"><span>11 月 4 日，<label class=\"sticker node group\"><span class=\"content\">🇨🇳 北京广播电视台</span></label>「</span><span class=\"c10\"><a class=\"c9\" href=\"https://www.weibo.com/2992050891/Qcf5HsEcB\">北京时间</a></span><span>」發布微博，內文包含「【#天眼俯瞰台湾#】尽在掌握！“吉林一号”俯瞰台湾，#任何台独分裂行动都逃不过天眼#跟踪。#台湾省可以用高德导航了」。同日，<label class=\"sticker node group\"><span class=\"content\">🇨🇳 香港大公文匯</span></label>「</span><span class=\"c10\"><a class=\"c9\" href=\"https://www.weibo.com/2632236847/Qcflp7AHa\">香港文匯網</a></span><span class=\"c7\">」發布微博，內文包含「#台湾省可以用高德导航了# 每一寸土地都清清楚楚，网友感慨：越来越近了~ ​​​」。</span></li><li class=\"\"><span>11 月 5 日，<label class=\"sticker node group\"><span class=\"content\">🇨🇳 国台办</span></label>「</span><span class=\"c10\"><a class=\"c9\" href=\"http://www.taiwan.cn/xwzx/xwfbh/gtbxwfbh/fbhwb/202511/t20251105_12732667.htm\">中国台湾网</a></span><span class=\"c7\">」發布文本「国台办 2025 年 11 月 5 日新闻发布会文字实录」，針對「湖北广电记者：据报道，高德地图在台湾实现全域覆盖，提供车道级导航、实时路况等功能，语音播报改用“左转”“右转”等本地化表述，发音清晰准确。岛内有网友称赞好用，表示“感觉和大陆距离近了很多”。对此有何评论？」，國台辦發言人張晗回應「我不掌握具体情况。我想说的是，对美好、便捷生活的追求是两岸同胞的权利。随着科学技术的发展创新、产业及服务的升级完善，越来越多的大陆物品、服务成为台湾民众的日常选择。我们对此喜闻乐见，希望越来越多台湾同胞可以享受到大陆的好产品、好服务」。 </span></li><li class=\"\"><span>11 月 5 日，<label class=\"sticker node group\"><span class=\"content\">🇨🇳 深圳广播电影电视集团</span></label>「</span><span class=\"c10\"><a class=\"c9\" href=\"https://www.weibo.com/6221932120/Qct7GdKsM\">直新闻</a></span><span>」發布微博，影片引用名嘴郭正亮、蔡正元在 11 月 4 日 <label class=\"sticker node group\"><span class=\"content\">旺中</span></label>「</span><span class=\"c10\"><a class=\"c9\" href=\"https://www.youtube.com/watch?v=fSTsa9HasZk&amp;t=6910s\">中天新聞</a></span><span class=\"c7\">」政論節目「中天辣晚報」中的發言片段，內文包含「大陆导航APP火到对岸 岛内名嘴都爱用！郭正亮：非常准 还可以选林志玲声音！蔡正元：比谷歌的还要好】台湾时事评论员蔡正元在节目中称赞高德地图的 3D 地图效果“比谷歌街景还要好”，台湾时事评论员郭正亮也在现场分享使用体验感：不仅具备双画面显示，还可以切换林志玲语音包！」。</span></li><li class=\"\"><span>11 月 8 日，<label class=\"sticker node group\"><span class=\"content\">🇨🇳 深圳广播电影电视集团</span></label>「</span><span class=\"c10\"><a class=\"c9\" href=\"https://www.weibo.com/6221932120/QcV0difhq\">直新闻</a></span><span class=\"c7\">」發布微博，內文包含「【台湾连串重大信号，统一步伐加速？】台海连串重大信号，统一的步伐正在加速？为何说反“独”促统这张大网处于收网阶段？高德地图入台，为什么让岛内某些人破防了？直言不讳，有话深聊」。</span></li></ul><div class=\"separator\"></div><div class=\"stickers\"></div><h2 class=\"c4\" id=\"h2-6\"><span class=\"c26\">精選人物</span></h2><h3 class=\"c4\" id=\"h.kawrshz1ens9\"><span class=\"c29\">黃安：在「台湾省」使用「高德地图」開心不已的影片「全网爆火」，宣稱會開心不已是因為「两岸统一的好日子早日到来」</span></h3><ul class=\"\"><li class=\"\"><span class=\"c7\">11 月份共有 158 則相關文本，佔比 0.44%。</span></li><li class=\"\"><span>11 月 1 日，藝人黃安發布 2 則微博。第 1 則</span><span class=\"c10\"><a class=\"c9\" href=\"https://www.weibo.com/2489313225/QbMfIB3yo\">貼文</a></span><span>宣稱「一觉醒来，导航都变了！  过去在台湾省开车导航，只能使用苹果自带的谷歌地图，提起这个宝里宝气的谷歌地图，语音播报的发音简直了」、「‘重庆北路’念成‘众庆北路’、‘二段’念成‘二吨’，最搞笑的是要台湾人过了前面路口，朝北前行 500 米…………台湾人找得着北吗？」、「今天要去一个地方，我无意中点开高德地图，吓了我一跳，不但可以导航，而且提供的信息跟在大陆开车的时候完全一样； 我又点开卫星图，我去，台湾岛上的每一条街都清清楚楚」、「癞蛤蟆要台湾人不要去、大陆同胞不要来，结果是每条街都被摸的一清二楚，哈哈哈哈哈！」、「 ‘等了好久终于等到今天’，今天起，在台湾省导航，就用高德！」。第 2 則</span><span class=\"c10\"><a class=\"c9\" href=\"https://www.weibo.com/2489313225/QbNDzF6zF\">貼文</a></span><span class=\"c7\">影片內容為其在台灣駕車、同時使用手機開啟高德導航 APP 的畫面，內文宣稱「台湾省可以使用高德导航啦！这就开着导航买早餐，忆苦思甜一番…」。</span></li><li class=\"\"><span>11 月 2-4 日間，包含 <label class=\"sticker node group\"><span class=\"content\">🇨🇳 国台办</span></label>「</span><span class=\"c10\"><a class=\"c9\" href=\"https://www.facebook.com/reel/854668273904555\">台灣網</a></span><span>」、<label class=\"sticker node group\"><span class=\"content\">🇨🇳 国务院</span></label>「</span><span class=\"c10\"><a class=\"c9\" href=\"http://www.weibo.com/1974576991/Qcaij4jYB\">环球时报</a></span><span>」、<label class=\"sticker node group\"><span class=\"content\">🇨🇳 福建日报</span></label>「</span><span class=\"c10\"><a class=\"c9\" href=\"https://www.douyin.com/video/7568401770368470310\">福建日报</a></span><span class=\"c7\">」在內的中共官媒於臉書、抖音、微博等平台共發布 128 則文本，放大傳播黃安在 11 月 1 日發布的 2 則微博。</span></li><li class=\"\"><span>11 月 5 日，<label class=\"sticker node group\"><span class=\"content\">🇨🇳 国台办</span></label>「</span><span class=\"c10\"><a class=\"c9\" href=\"http://www.taiwan.cn/xwzx/xwfbh/gtbxwfbh/fbhwb/202511/t20251105_12732667.htm\">中国台湾网</a></span><span class=\"c7\">」發布文本「国台办 2025 年 11 月 5 日新闻发布会文字实录」，針對「湖北广电记者：据报道，高德地图在台湾实现全域覆盖，提供车道级导航、实时路况等功能，语音播报改用“左转”“右转”等本地化表述，发音清晰准确。岛内有网友称赞好用，表示“感觉和大陆距离近了很多”。对此有何评论？」，國台辦發言人張晗回應「我不掌握具体情况。我想说的是，对美好、便捷生活的追求是两岸同胞的权利。随着科学技术的发展创新、产业及服务的升级完善，越来越多的大陆物品、服务成为台湾民众的日常选择。我们对此喜闻乐见，希望越来越多台湾同胞可以享受到大陆的好产品、好服务」。  </span></li><li class=\"\"><span>11 月 8 日， <label class=\"sticker node group\"><span class=\"content\">🇨🇳 北京日报</span></label>「</span><span class=\"c10\"><a class=\"c9\" href=\"http://www.weibo.com/1893892941/QcTzLaweK\">北京日报</a></span><span class=\"c7\">」發布微博，內文包含「#黄安回应导航视频爆火#“等了好久终于等到今天，梦了好久终于把梦实现”。11月8日，在接受北京日报 记者专访时，台湾歌手黄安 借这句经典歌词，道出了他对近日导航软件在台使用引发热议的深层感悟」、「面对全网爆火的视频和国台办的正式回应，黄安表示，这份喜悦“不只是导航软件的使用，更是两岸统一的好日子早日到来的心情”。一句“终于把梦实现”，既是对当下两岸科技互联互通的欣慰，更是对实现祖国统一的热切期盼」。</span></li></ul><div class=\"separator\"></div><div class=\"stickers\"></div><h2 class=\"c4\" id=\"h2-7\"><span class=\"c26\">精選美食</span></h2><h3 class=\"c4\" id=\"h.mxtta88vcvoo\"><span>青岛</span><span>嘎啦</span><span class=\"c29\">、舟山黄鱼、连云港梭子蟹：暫停進口日本水產品是不得不采取嚴厲堅決的反制措施，沿海地區的網友紛紛曬出家鄉特產表示支持</span></h3><ul class=\"\"><li class=\"\"><span class=\"c7\">11 月份共有 9 則相關文本，佔比 0.003%。</span></li><li class=\"\"><span>11 月 20 日，<label class=\"sticker node group\"><span class=\"content\">🇨🇳 江苏新华报业传媒</span></label>「</span><span class=\"c10\"><a class=\"c9\" href=\"https://www.weibo.com/1653603955/QeFIKhn6a\">扬子晚报</a></span><span>」發布微博，內文宣稱「19日，中国政府向日本政府通报，暂停进口日本水产品。外交部发言人毛宁表示，即使日本水产品向中国出口，也不会有市场。关于外交部这一回应，我国沿海地区的网友纷纷晒出家乡特产表示支持——青岛“嘎啦”、舟山黄鱼，还有连云港梭子蟹，国产海鲜不仅品类丰富，而且性价比拉满！」、「日本馬上要沒有大熊貓了」。同日，「</span><span class=\"c10\"><a class=\"c9\" href=\"https://www.douyin.com/video/7574603001537580314\">扬子晚报</a></span><span class=\"c7\">」發布包含相同內容抖音。</span></li><li class=\"\"><span>同日，<label class=\"sticker node group\"><span class=\"content\">🇨🇳 江苏新华报业传媒</span></label>「</span><span class=\"c10\"><a class=\"c9\" href=\"https://www.weibo.com/1653603955/QeFSCe7cs\">扬子晚报</a></span><span class=\"c7\">」發布微博，內文宣稱「网友晒嘎啦黄鱼梭子蟹力挺外交部」、「中国鳗鱼撑起全球八成供应」、「中方将不得不采取严厉坚决的反制措施」。</span></li></ul><h3 class=\"c4\" id=\"h.8nwsbni03upp\"><span class=\"c29\">瑞幸咖啡：體驗過的台灣民眾表示「趕緊多開幾家」、在島內「掀起風潮」，綠營「緊張壞了」，被輿論嘲諷「連咖啡都怕」</span></h3><ul class=\"\"><li class=\"\"><span class=\"c7\">11 月份共有 6 則相關文本，佔比 0.002%。</span></li><li class=\"\"><span>11 月 26 日，<label class=\"sticker node group\"><span class=\"content\">🇨🇳 香港中國通訊社</span></label>「</span><span class=\"c10\"><a class=\"c9\" href=\"https://www.hkcna.hk/docDetail.jsp?id=101174607&amp;channel=2805\">香港新聞網</a></span><span class=\"c7\">」發布文本「台媒指瑞幸咖啡將在台灣開設門店」，內文宣稱「中國大陸連鎖咖啡品牌瑞幸咖啡據傳將於 12 月登台，首家門店選址在台北市南京東路商圈」、「曾體驗過瑞幸咖啡的台灣民眾在社交媒體表示，瑞幸價格親民服務又好，“趕緊多開幾家”」。</span></li><li class=\"\"><span>11 月 26 日，<label class=\"sticker node group\"><span class=\"content\">🇨🇳 香港中國通訊社</span></label>「</span><span class=\"c10\"><a class=\"c9\" href=\"https://www.hkcna.hk/docDetail.jsp?id=101174621&amp;channel=2805\">香港新聞網</a></span><span>」發布文本「瑞幸咖啡進軍台灣？台綠營緊張壞了」，內文宣稱「台灣近日傳出大陸的瑞幸咖啡即將登陸台灣，引發不少民眾期待，認為它會被“喝爆”、在島內掀起風潮」、「台經濟部門宣稱，有關入台事宜是否涉陸資疑慮，會持續關注，必要時也會啟動行政調查。對此，台輿論諷刺，民進黨當局“逢陸跳腳”，凡事都政治化！諷刺“不會連咖啡都怕吧？」、「事實上，近年來，在台灣廣受歡迎的大陸風味遠不止咖啡茶飲。各類休閒零食如辣花生、螺螄粉、魔芋爽、鮮花餅等，以及地方美食和特色餐飲如梅花糕、酸菜魚、椰子雞等，也接連在台灣掀起一波波美食熱潮，持續引發民眾的品嘗與討論熱情。正如中國國務院台辦發言人朱鳳蓮此前所說，這“充分說明兩岸同文同種、同風同俗，有一樣的美食愛好，一樣的文化品味”」。同日，<label class=\"sticker node group\"><span class=\"content\">🇨🇳 香港中國通訊社</span></label>「</span><span class=\"c10\"><a class=\"c9\" href=\"http://www.weibo.com/5999251130/QfEzCa9Es\">香港中通社</a></span><span class=\"c7\">」發布內文完全相同之微博。</span></li></ul>",
	"articleID": "_DA_126",
	"publicURL": "https://docs.google.com/document/d/e/2PACX-1vR6XqQ-7RWPnVKXiJCdVfzaDpaZTbb1fmIIl2Dp9bf-cbsP_eLVhmhoVBXkIeIbkojFJcxrxQezksfl/pub",
	"locale": "_tw",
	"publishedAt": "2025/12/15 10:00"
}